Classfile jar:file:///C:/wamp64/www/frontend/php-frontend/php-backend/PhpPlugin/iPAYPlugin/ipayPipe.jar!/com/fss/plugin/ParseResouce.class
  Last modified 17-Jan-2025; size 16138 bytes
  SHA-256 checksum cb6a57bd363f28edf40a10b58d77c68840f911d39a062719da640251ba0aaf80
  Compiled from "ParseResouce.java"
public class com.fss.plugin.ParseResouce
  minor version: 0
  major version: 52
  flags: (0x0021) ACC_PUBLIC, ACC_SUPER
  this_class: #1                          // com/fss/plugin/ParseResouce
  super_class: #3                         // java/lang/Object
  interfaces: 0, fields: 7, methods: 21, attributes: 1
Constant pool:
    #1 = Class              #2            // com/fss/plugin/ParseResouce
    #2 = Utf8               com/fss/plugin/ParseResouce
    #3 = Class              #4            // java/lang/Object
    #4 = Utf8               java/lang/Object
    #5 = Utf8               SEPERATOR
    #6 = Utf8               Ljava/lang/String;
    #7 = Utf8               encrKekStr
    #8 = Utf8               ConstantValue
    #9 = String             #10           // 3535353330363331343038363230373832313932313537373433353833313137
   #10 = Utf8               3535353330363331343038363230373832313932313537373433353833313137
   #11 = Utf8               encrKeystoreStr
   #12 = String             #13           // 3c6440709a54bfa0932bedbca57df396dbc0df48f98b580a9ab91c1d84ecca69c0976abe59bd94974ea15824f46c4202
   #13 = Utf8               3c6440709a54bfa0932bedbca57df396dbc0df48f98b580a9ab91c1d84ecca69c0976abe59bd94974ea15824f46c4202
   #14 = Utf8               encrKeyStr
   #15 = String             #16           // 3d6f4f729350bfa5972de6b1a47efd93ddcbd14afe8c520d9fbe1d1d81e2c96e70d592b22ee13e7443b8f2d222a01e45
   #16 = Utf8               3d6f4f729350bfa5972de6b1a47efd93ddcbd14afe8c520d9fbe1d1d81e2c96e70d592b22ee13e7443b8f2d222a01e45
   #17 = Utf8               DEK
   #18 = Utf8               Ljava/security/Key;
   #19 = Utf8               KEYSTORE_PWD
   #20 = Utf8               KEY_PWD
   #21 = Utf8               <clinit>
   #22 = Utf8               ()V
   #23 = Utf8               Code
   #24 = Fieldref           #25.#27       // java/io/File.separator:Ljava/lang/String;
   #25 = Class              #26           // java/io/File
   #26 = Utf8               java/io/File
   #27 = NameAndType        #28:#6        // separator:Ljava/lang/String;
   #28 = Utf8               separator
   #29 = Fieldref           #1.#30        // com/fss/plugin/ParseResouce.SEPERATOR:Ljava/lang/String;
   #30 = NameAndType        #5:#6         // SEPERATOR:Ljava/lang/String;
   #31 = Fieldref           #1.#32        // com/fss/plugin/ParseResouce.DEK:Ljava/security/Key;
   #32 = NameAndType        #17:#18       // DEK:Ljava/security/Key;
   #33 = Fieldref           #1.#34        // com/fss/plugin/ParseResouce.KEYSTORE_PWD:Ljava/lang/String;
   #34 = NameAndType        #19:#6        // KEYSTORE_PWD:Ljava/lang/String;
   #35 = Fieldref           #1.#36        // com/fss/plugin/ParseResouce.KEY_PWD:Ljava/lang/String;
   #36 = NameAndType        #20:#6        // KEY_PWD:Ljava/lang/String;
   #37 = Class              #38           // org/bouncycastle/jce/provider/BouncyCastleProvider
   #38 = Utf8               org/bouncycastle/jce/provider/BouncyCastleProvider
   #39 = Methodref          #37.#40       // org/bouncycastle/jce/provider/BouncyCastleProvider."<init>":()V
   #40 = NameAndType        #41:#22       // "<init>":()V
   #41 = Utf8               <init>
   #42 = Methodref          #43.#45       // java/security/Security.addProvider:(Ljava/security/Provider;)I
   #43 = Class              #44           // java/security/Security
   #44 = Utf8               java/security/Security
   #45 = NameAndType        #46:#47       // addProvider:(Ljava/security/Provider;)I
   #46 = Utf8               addProvider
   #47 = Utf8               (Ljava/security/Provider;)I
   #48 = Utf8               LineNumberTable
   #49 = Utf8               LocalVariableTable
   #50 = Methodref          #3.#40        // java/lang/Object."<init>":()V
   #51 = Utf8               this
   #52 = Utf8               Lcom/fss/plugin/ParseResouce;
   #53 = Utf8               loadOldKeyStore
   #54 = Utf8               (Ljava/lang/String;)Ljava/security/Key;
   #55 = Utf8               Exceptions
   #56 = Class              #57           // java/lang/Exception
   #57 = Utf8               java/lang/Exception
   #58 = Methodref          #1.#59        // com/fss/plugin/ParseResouce.loadOldKeys:(Ljava/lang/String;)Ljava/security/Key;
   #59 = NameAndType        #60:#54       // loadOldKeys:(Ljava/lang/String;)Ljava/security/Key;
   #60 = Utf8               loadOldKeys
   #61 = Utf8               keystorePath
   #62 = Utf8               key
   #63 = Utf8               getKeystorePwd
   #64 = Utf8               ()Ljava/lang/String;
   #65 = Class              #66           // java/lang/String
   #66 = Utf8               java/lang/String
   #67 = Methodref          #1.#68        // com/fss/plugin/ParseResouce.hex2Alpha:(Ljava/lang/String;)Ljava/lang/String;
   #68 = NameAndType        #69:#70       // hex2Alpha:(Ljava/lang/String;)Ljava/lang/String;
   #69 = Utf8               hex2Alpha
   #70 = Utf8               (Ljava/lang/String;)Ljava/lang/String;
   #71 = Methodref          #72.#74       // com/fss/plugin/AESAlgorithm.generateAESKey:(Ljava/lang/String;)Ljavax/crypto/SecretKey;
   #72 = Class              #73           // com/fss/plugin/AESAlgorithm
   #73 = Utf8               com/fss/plugin/AESAlgorithm
   #74 = NameAndType        #75:#76       // generateAESKey:(Ljava/lang/String;)Ljavax/crypto/SecretKey;
   #75 = Utf8               generateAESKey
   #76 = Utf8               (Ljava/lang/String;)Ljavax/crypto/SecretKey;
   #77 = Methodref          #72.#78       // com/fss/plugin/AESAlgorithm.hexStringToByteArray:(Ljava/lang/String;)[B
   #78 = NameAndType        #79:#80       // hexStringToByteArray:(Ljava/lang/String;)[B
   #79 = Utf8               hexStringToByteArray
   #80 = Utf8               (Ljava/lang/String;)[B
   #81 = Methodref          #72.#82       // com/fss/plugin/AESAlgorithm.decrypt:(Ljava/security/Key;[B)[B
   #82 = NameAndType        #83:#84       // decrypt:(Ljava/security/Key;[B)[B
   #83 = Utf8               decrypt
   #84 = Utf8               (Ljava/security/Key;[B)[B
   #85 = Methodref          #65.#86       // java/lang/String."<init>":([B)V
   #86 = NameAndType        #41:#87       // "<init>":([B)V
   #87 = Utf8               ([B)V
   #88 = Utf8               StackMapTable
   #89 = Utf8               getKeyPwd
   #90 = Utf8               loadNewKeyStore
   #91 = Methodref          #1.#92        // com/fss/plugin/ParseResouce.loadNewKeys:(Ljava/lang/String;)Ljava/security/Key;
   #92 = NameAndType        #93:#54       // loadNewKeys:(Ljava/lang/String;)Ljava/security/Key;
   #93 = Utf8               loadNewKeys
   #94 = Class              #95           // java/security/KeyStoreException
   #95 = Utf8               java/security/KeyStoreException
   #96 = Class              #97           // java/security/NoSuchAlgorithmException
   #97 = Utf8               java/security/NoSuchAlgorithmException
   #98 = Class              #99           // java/security/cert/CertificateException
   #99 = Utf8               java/security/cert/CertificateException
  #100 = Class              #101          // java/io/IOException
  #101 = Utf8               java/io/IOException
  #102 = Class              #103          // java/security/UnrecoverableKeyException
  #103 = Utf8               java/security/UnrecoverableKeyException
  #104 = Class              #105          // java/lang/SecurityException
  #105 = Utf8               java/lang/SecurityException
  #106 = Methodref          #25.#107      // java/io/File."<init>":(Ljava/lang/String;)V
  #107 = NameAndType        #41:#108      // "<init>":(Ljava/lang/String;)V
  #108 = Utf8               (Ljava/lang/String;)V
  #109 = Methodref          #25.#110      // java/io/File.exists:()Z
  #110 = NameAndType        #111:#112     // exists:()Z
  #111 = Utf8               exists
  #112 = Utf8               ()Z
  #113 = String             #114          // JCEKS
  #114 = Utf8               JCEKS
  #115 = Methodref          #116.#118     // java/security/KeyStore.getInstance:(Ljava/lang/String;)Ljava/security/KeyStore;
  #116 = Class              #117          // java/security/KeyStore
  #117 = Utf8               java/security/KeyStore
  #118 = NameAndType        #119:#120     // getInstance:(Ljava/lang/String;)Ljava/security/KeyStore;
  #119 = Utf8               getInstance
  #120 = Utf8               (Ljava/lang/String;)Ljava/security/KeyStore;
  #121 = String             #122          // password
  #122 = Utf8               password
  #123 = Methodref          #1.#124       // com/fss/plugin/ParseResouce.getCharArray:(Ljava/lang/String;)[C
  #124 = NameAndType        #125:#126     // getCharArray:(Ljava/lang/String;)[C
  #125 = Utf8               getCharArray
  #126 = Utf8               (Ljava/lang/String;)[C
  #127 = Class              #128          // java/io/FileInputStream
  #128 = Utf8               java/io/FileInputStream
  #129 = Methodref          #127.#130     // java/io/FileInputStream."<init>":(Ljava/io/File;)V
  #130 = NameAndType        #41:#131      // "<init>":(Ljava/io/File;)V
  #131 = Utf8               (Ljava/io/File;)V
  #132 = Methodref          #116.#133     // java/security/KeyStore.load:(Ljava/io/InputStream;[C)V
  #133 = NameAndType        #134:#135     // load:(Ljava/io/InputStream;[C)V
  #134 = Utf8               load
  #135 = Utf8               (Ljava/io/InputStream;[C)V
  #136 = String             #137          // pgkey
  #137 = Utf8               pgkey
  #138 = Methodref          #116.#139     // java/security/KeyStore.getKey:(Ljava/lang/String;[C)Ljava/security/Key;
  #139 = NameAndType        #140:#141     // getKey:(Ljava/lang/String;[C)Ljava/security/Key;
  #140 = Utf8               getKey
  #141 = Utf8               (Ljava/lang/String;[C)Ljava/security/Key;
  #142 = Methodref          #143.#145     // java/io/InputStream.close:()V
  #143 = Class              #144          // java/io/InputStream
  #144 = Utf8               java/io/InputStream
  #145 = NameAndType        #146:#22      // close:()V
  #146 = Utf8               close
  #147 = Class              #148          // java/io/EOFException
  #148 = Utf8               java/io/EOFException
  #149 = Utf8               keystorelocation
  #150 = Utf8               file
  #151 = Utf8               Ljava/io/File;
  #152 = Utf8               ks
  #153 = Utf8               Ljava/security/KeyStore;
  #154 = Utf8               pass
  #155 = Utf8               [C
  #156 = Utf8               is
  #157 = Utf8               Ljava/io/InputStream;
  #158 = Utf8               ex
  #159 = Utf8               Ljava/io/EOFException;
  #160 = Class              #161          // java/security/Key
  #161 = Utf8               java/security/Key
  #162 = Class              #155          // "[C"
  #163 = Class              #164          // java/lang/Throwable
  #164 = Utf8               java/lang/Throwable
  #165 = Methodref          #1.#166       // com/fss/plugin/ParseResouce.getKeystorePwd:()Ljava/lang/String;
  #166 = NameAndType        #63:#64       // getKeystorePwd:()Ljava/lang/String;
  #167 = Methodref          #65.#168      // java/lang/String.toCharArray:()[C
  #168 = NameAndType        #169:#170     // toCharArray:()[C
  #169 = Utf8               toCharArray
  #170 = Utf8               ()[C
  #171 = Methodref          #1.#172       // com/fss/plugin/ParseResouce.getKeyPwd:()Ljava/lang/String;
  #172 = NameAndType        #89:#64       // getKeyPwd:()Ljava/lang/String;
  #173 = Utf8               hexString
  #174 = Utf8               ([B)Ljava/lang/String;
  #175 = Class              #176          // java/lang/StringBuffer
  #176 = Utf8               java/lang/StringBuffer
  #177 = Methodref          #175.#178     // java/lang/StringBuffer."<init>":(I)V
  #178 = NameAndType        #41:#179      // "<init>":(I)V
  #179 = Utf8               (I)V
  #180 = Methodref          #181.#183     // java/lang/Character.forDigit:(II)C
  #181 = Class              #182          // java/lang/Character
  #182 = Utf8               java/lang/Character
  #183 = NameAndType        #184:#185     // forDigit:(II)C
  #184 = Utf8               forDigit
  #185 = Utf8               (II)C
  #186 = Methodref          #181.#187     // java/lang/Character.toUpperCase:(C)C
  #187 = NameAndType        #188:#189     // toUpperCase:(C)C
  #188 = Utf8               toUpperCase
  #189 = Utf8               (C)C
  #190 = Methodref          #175.#191     // java/lang/StringBuffer.append:(C)Ljava/lang/StringBuffer;
  #191 = NameAndType        #192:#193     // append:(C)Ljava/lang/StringBuffer;
  #192 = Utf8               append
  #193 = Utf8               (C)Ljava/lang/StringBuffer;
  #194 = Methodref          #175.#195     // java/lang/StringBuffer.toString:()Ljava/lang/String;
  #195 = NameAndType        #196:#64      // toString:()Ljava/lang/String;
  #196 = Utf8               toString
  #197 = Utf8               abyte0
  #198 = Utf8               [B
  #199 = Utf8               stringbuffer
  #200 = Utf8               Ljava/lang/StringBuffer;
  #201 = Utf8               i
  #202 = Utf8               I
  #203 = Utf8               c
  #204 = Utf8               C
  #205 = Utf8               c1
  #206 = Methodref          #65.#207      // java/lang/String.length:()I
  #207 = NameAndType        #208:#209     // length:()I
  #208 = Utf8               length
  #209 = Utf8               ()I
  #210 = Methodref          #175.#40      // java/lang/StringBuffer."<init>":()V
  #211 = Methodref          #65.#212      // java/lang/String.substring:(II)Ljava/lang/String;
  #212 = NameAndType        #213:#214     // substring:(II)Ljava/lang/String;
  #213 = Utf8               substring
  #214 = Utf8               (II)Ljava/lang/String;
  #215 = Methodref          #216.#218     // java/lang/Integer.valueOf:(Ljava/lang/String;I)Ljava/lang/Integer;
  #216 = Class              #217          // java/lang/Integer
  #217 = Utf8               java/lang/Integer
  #218 = NameAndType        #219:#220     // valueOf:(Ljava/lang/String;I)Ljava/lang/Integer;
  #219 = Utf8               valueOf
  #220 = Utf8               (Ljava/lang/String;I)Ljava/lang/Integer;
  #221 = Methodref          #216.#222     // java/lang/Integer.intValue:()I
  #222 = NameAndType        #223:#209     // intValue:()I
  #223 = Utf8               intValue
  #224 = Utf8               data
  #225 = Utf8               len
  #226 = Utf8               sb
  #227 = Utf8               j
  #228 = Utf8               alpha2Hex
  #229 = Methodref          #216.#230     // java/lang/Integer.toHexString:(I)Ljava/lang/String;
  #230 = NameAndType        #231:#232     // toHexString:(I)Ljava/lang/String;
  #231 = Utf8               toHexString
  #232 = Utf8               (I)Ljava/lang/String;
  #233 = Methodref          #65.#234      // java/lang/String.toUpperCase:()Ljava/lang/String;
  #234 = NameAndType        #188:#64      // toUpperCase:()Ljava/lang/String;
  #235 = String             #236          // 0
  #236 = Utf8               0
  #237 = Methodref          #175.#238     // java/lang/StringBuffer.append:(Ljava/lang/String;)Ljava/lang/StringBuffer;
  #238 = NameAndType        #192:#239     // append:(Ljava/lang/String;)Ljava/lang/StringBuffer;
  #239 = Utf8               (Ljava/lang/String;)Ljava/lang/StringBuffer;
  #240 = Utf8               alpha
  #241 = Utf8               count
  #242 = String             #243          //
  #243 = Utf8
  #244 = Methodref          #65.#245      // java/lang/String.equalsIgnoreCase:(Ljava/lang/String;)Z
  #245 = NameAndType        #246:#247     // equalsIgnoreCase:(Ljava/lang/String;)Z
  #246 = Utf8               equalsIgnoreCase
  #247 = Utf8               (Ljava/lang/String;)Z
  #248 = Utf8               str
  #249 = Utf8               getCGNData
  #250 = Utf8               (Ljava/lang/String;Ljava/lang/String;Ljava/security/Key;)Ljava/lang/String;
  #251 = Methodref          #1.#252       // com/fss/plugin/ParseResouce.createCGZFileFromCGN:(Ljava/lang/String;Ljava/security/Key;)Ljava/lang/String;
  #252 = NameAndType        #253:#254     // createCGZFileFromCGN:(Ljava/lang/String;Ljava/security/Key;)Ljava/lang/String;
  #253 = Utf8               createCGZFileFromCGN
  #254 = Utf8               (Ljava/lang/String;Ljava/security/Key;)Ljava/lang/String;
  #255 = String             #256          // !!Exception!!
  #256 = Utf8               !!Exception!!
  #257 = Methodref          #65.#258      // java/lang/String.contains:(Ljava/lang/CharSequence;)Z
  #258 = NameAndType        #259:#260     // contains:(Ljava/lang/CharSequence;)Z
  #259 = Utf8               contains
  #260 = Utf8               (Ljava/lang/CharSequence;)Z
  #261 = Class              #262          // java/lang/StringBuilder
  #262 = Utf8               java/lang/StringBuilder
  #263 = String             #264          // !!Exception!! while retrieving cgn data :
  #264 = Utf8               !!Exception!! while retrieving cgn data :
  #265 = Methodref          #261.#107     // java/lang/StringBuilder."<init>":(Ljava/lang/String;)V
  #266 = Methodref          #267.#269     // java/security/InvalidKeyException.getMessage:()Ljava/lang/String;
  #267 = Class              #268          // java/security/InvalidKeyException
  #268 = Utf8               java/security/InvalidKeyException
  #269 = NameAndType        #270:#64      // getMessage:()Ljava/lang/String;
  #270 = Utf8               getMessage
  #271 = Methodref          #261.#272     // java/lang/StringBuilder.append:(Ljava/lang/String;)Ljava/lang/StringBuilder;
  #272 = NameAndType        #192:#273     // append:(Ljava/lang/String;)Ljava/lang/StringBuilder;
  #273 = Utf8               (Ljava/lang/String;)Ljava/lang/StringBuilder;
  #274 = Fieldref           #275.#277     // com/fss/plugin/MAC.fullErrorSplliter:Ljava/lang/String;
  #275 = Class              #276          // com/fss/plugin/MAC
  #276 = Utf8               com/fss/plugin/MAC
  #277 = NameAndType        #278:#6       // fullErrorSplliter:Ljava/lang/String;
  #278 = Utf8               fullErrorSplliter
  #279 = Methodref          #275.#280     // com/fss/plugin/MAC.fullStackTrace:(Ljava/lang/Exception;)Ljava/lang/String;
  #280 = NameAndType        #281:#282     // fullStackTrace:(Ljava/lang/Exception;)Ljava/lang/String;
  #281 = Utf8               fullStackTrace
  #282 = Utf8               (Ljava/lang/Exception;)Ljava/lang/String;
  #283 = Methodref          #261.#195     // java/lang/StringBuilder.toString:()Ljava/lang/String;
  #284 = Methodref          #65.#107      // java/lang/String."<init>":(Ljava/lang/String;)V
  #285 = Methodref          #96.#269      // java/security/NoSuchAlgorithmException.getMessage:()Ljava/lang/String;
  #286 = Methodref          #287.#269     // javax/crypto/NoSuchPaddingException.getMessage:()Ljava/lang/String;
  #287 = Class              #288          // javax/crypto/NoSuchPaddingException
  #288 = Utf8               javax/crypto/NoSuchPaddingException
  #289 = Methodref          #290.#269     // javax/crypto/ShortBufferException.getMessage:()Ljava/lang/String;
  #290 = Class              #291          // javax/crypto/ShortBufferException
  #291 = Utf8               javax/crypto/ShortBufferException
  #292 = Methodref          #293.#269     // javax/crypto/IllegalBlockSizeException.getMessage:()Ljava/lang/String;
  #293 = Class              #294          // javax/crypto/IllegalBlockSizeException
  #294 = Utf8               javax/crypto/IllegalBlockSizeException
  #295 = Methodref          #296.#269     // javax/crypto/BadPaddingException.getMessage:()Ljava/lang/String;
  #296 = Class              #297          // javax/crypto/BadPaddingException
  #297 = Utf8               javax/crypto/BadPaddingException
  #298 = Methodref          #100.#269     // java/io/IOException.getMessage:()Ljava/lang/String;
  #299 = Methodref          #65.#300      // java/lang/String.valueOf:(Ljava/lang/Object;)Ljava/lang/String;
  #300 = NameAndType        #219:#301     // valueOf:(Ljava/lang/Object;)Ljava/lang/String;
  #301 = Utf8               (Ljava/lang/Object;)Ljava/lang/String;
  #302 = String             #303          // .xml
  #303 = Utf8               .xml
  #304 = Methodref          #1.#305       // com/fss/plugin/ParseResouce.extractZIPAndReadXML:(Ljava/lang/String;Ljava/lang/String;)[B
  #305 = NameAndType        #306:#307     // extractZIPAndReadXML:(Ljava/lang/String;Ljava/lang/String;)[B
  #306 = Utf8               extractZIPAndReadXML
  #307 = Utf8               (Ljava/lang/String;Ljava/lang/String;)[B
  #308 = String             #309          // !!Exception!! while extracting and reading xml data :
  #309 = Utf8               !!Exception!! while extracting and reading xml data :
  #310 = Methodref          #311.#269     // java/lang/IllegalStateException.getMessage:()Ljava/lang/String;
  #311 = Class              #312          // java/lang/IllegalStateException
  #312 = Utf8               java/lang/IllegalStateException
  #313 = String             #314          // !!Exception!! Alias Name does not Exits.
  #314 = Utf8               !!Exception!! Alias Name does not Exits.
  #315 = String             #316          // Record not found for this Alias Name
  #316 = Utf8               Record not found for this Alias Name
  #317 = String             #318          //  in the resource file location :
  #318 = Utf8                in the resource file location :
  #319 = InterfaceMethodref #160.#320     // java/security/Key.getEncoded:()[B
  #320 = NameAndType        #321:#322     // getEncoded:()[B
  #321 = Utf8               getEncoded
  #322 = Utf8               ()[B
  #323 = Methodref          #1.#324       // com/fss/plugin/ParseResouce.decrypt:([BLjava/security/Key;)[B
  #324 = NameAndType        #83:#325      // decrypt:([BLjava/security/Key;)[B
  #325 = Utf8               ([BLjava/security/Key;)[B
  #326 = String             #327          // !!Exception!! while decrypting xml data :
  #327 = Utf8               !!Exception!! while decrypting xml data :
  #328 = Methodref          #56.#269      // java/lang/Exception.getMessage:()Ljava/lang/String;
  #329 = String             #330          // resource.cgz
  #330 = Utf8               resource.cgz
  #331 = Methodref          #1.#332       // com/fss/plugin/ParseResouce.deleteFile:(Ljava/lang/String;)V
  #332 = NameAndType        #333:#108     // deleteFile:(Ljava/lang/String;)V
  #333 = Utf8               deleteFile
  #334 = String             #335          // !!Exception!! while deleting cgz file :
  #335 = Utf8               !!Exception!! while deleting cgz file :
  #336 = String             #337          // !!Exception!! While decrypting xml data.
  #337 = Utf8               !!Exception!! While decrypting xml data.
  #338 = String             #339          // Error while decrypting xml data or null
  #339 = Utf8               Error while decrypting xml data or null
  #340 = Utf8               resourcePath
  #341 = Utf8               aliasName
  #342 = Utf8               resp
  #343 = Utf8               e
  #344 = Utf8               Ljava/security/InvalidKeyException;
  #345 = Utf8               Ljava/security/NoSuchAlgorithmException;
  #346 = Utf8               Ljavax/crypto/NoSuchPaddingException;
  #347 = Utf8               Ljavax/crypto/ShortBufferException;
  #348 = Utf8               Ljavax/crypto/IllegalBlockSizeException;
  #349 = Utf8               Ljavax/crypto/BadPaddingException;
  #350 = Utf8               Ljava/io/IOException;
  #351 = Utf8               xmlData
  #352 = Utf8               decryptedText
  #353 = Utf8               e1
  #354 = Utf8               Ljava/lang/IllegalStateException;
  #355 = Utf8               keyByte
  #356 = Utf8               Ljava/lang/Exception;
  #357 = Class              #198          // "[B"
  #358 = Utf8               getCGNDataAES
  #359 = Methodref          #1.#360       // com/fss/plugin/ParseResouce.createCGZFileFromCGNAES:(Ljava/lang/String;Ljava/security/Key;)Ljava/lang/String;
  #360 = NameAndType        #361:#254     // createCGZFileFromCGNAES:(Ljava/lang/String;Ljava/security/Key;)Ljava/lang/String;
  #361 = Utf8               createCGZFileFromCGNAES
  #362 = String             #363          // !!Exception!! while retrieving AES cgn data :
  #363 = Utf8               !!Exception!! while retrieving AES cgn data :
  #364 = String             #365          // !!Exception!! while retrieving AES vcgn data :
  #365 = Utf8               !!Exception!! while retrieving AES vcgn data :
  #366 = Methodref          #1.#367       // com/fss/plugin/ParseResouce.extractZIPAndReadXMLAES:(Ljava/lang/String;Ljava/lang/String;)[B
  #367 = NameAndType        #368:#307     // extractZIPAndReadXMLAES:(Ljava/lang/String;Ljava/lang/String;)[B
  #368 = Utf8               extractZIPAndReadXMLAES
  #369 = String             #370          // !!Exception!! while extracting and reading AES xml data :
  #370 = Utf8               !!Exception!! while extracting and reading AES xml data :
  #371 = String             #372          // !!Exception!! while decrypting AES xml data :
  #372 = Utf8               !!Exception!! while decrypting AES xml data :
  #373 = String             #374          // AES_resource.cgz
  #374 = Utf8               AES_resource.cgz
  #375 = String             #376          // !!Exception!! while deleting AES cgz file :
  #376 = Utf8               !!Exception!! while deleting AES cgz file :
  #377 = String             #378          // !!Exception!! While decrypting AES xml data.
  #378 = Utf8               !!Exception!! While decrypting AES xml data.
  #379 = String             #380          // Error while decrypting AES xml data or null
  #380 = Utf8               Error while decrypting AES xml data or null
  #381 = Methodref          #25.#382      // java/io/File.createNewFile:()Z
  #382 = NameAndType        #383:#112     // createNewFile:()Z
  #383 = Utf8               createNewFile
  #384 = String             #385          // resource.cgn
  #385 = Utf8               resource.cgn
  #386 = Class              #387          // java/io/BufferedInputStream
  #387 = Utf8               java/io/BufferedInputStream
  #388 = Methodref          #386.#389     // java/io/BufferedInputStream."<init>":(Ljava/io/InputStream;)V
  #389 = NameAndType        #41:#390      // "<init>":(Ljava/io/InputStream;)V
  #390 = Utf8               (Ljava/io/InputStream;)V
  #391 = Class              #392          // java/io/FileOutputStream
  #392 = Utf8               java/io/FileOutputStream
  #393 = Methodref          #391.#130     // java/io/FileOutputStream."<init>":(Ljava/io/File;)V
  #394 = Methodref          #25.#395      // java/io/File.length:()J
  #395 = NameAndType        #208:#396     // length:()J
  #396 = Utf8               ()J
  #397 = Methodref          #386.#398     // java/io/BufferedInputStream.read:([B)I
  #398 = NameAndType        #399:#400     // read:([B)I
  #399 = Utf8               read
  #400 = Utf8               ([B)I
  #401 = Methodref          #402.#404     // java/io/OutputStream.write:([B)V
  #402 = Class              #403          // java/io/OutputStream
  #403 = Utf8               java/io/OutputStream
  #404 = NameAndType        #405:#87      // write:([B)V
  #405 = Utf8               write
  #406 = Methodref          #402.#407     // java/io/OutputStream.flush:()V
  #407 = NameAndType        #408:#22      // flush:()V
  #408 = Utf8               flush
  #409 = Class              #410          // java/io/FileNotFoundException
  #410 = Utf8               java/io/FileNotFoundException
  #411 = String             #412          // !!Exception!! File Not found in the Path Please validate the resource.cgn path :
  #412 = Utf8               !!Exception!! File Not found in the Path Please validate the resource.cgn path :
  #413 = String             #414          // resource.cgz :
  #414 = Utf8               resource.cgz :
  #415 = String             #416          // !!Exception!! in decrypting resource.cgn data :
  #416 = Utf8               !!Exception!! in decrypting resource.cgn data :
  #417 = Methodref          #402.#145     // java/io/OutputStream.close:()V
  #418 = Methodref          #386.#145     // java/io/BufferedInputStream.close:()V
  #419 = Utf8               cgzFile
  #420 = Utf8               cgnFile
  #421 = Utf8               Ljava/io/BufferedInputStream;
  #422 = Utf8               os
  #423 = Utf8               Ljava/io/OutputStream;
  #424 = Utf8               cgnFileLength
  #425 = Utf8               cgnFileData
  #426 = Utf8               decryptedCgnFileData
  #427 = String             #428          // AES_resource.cgn
  #428 = Utf8               AES_resource.cgn
  #429 = String             #430          // AES_resource.cgz :
  #430 = Utf8               AES_resource.cgz :
  #431 = String             #432          // !!Exception!! in decrypting AES_resource.cgn data :
  #432 = Utf8               !!Exception!! in decrypting AES_resource.cgn data :
  #433 = Class              #434          // java/io/ByteArrayOutputStream
  #434 = Utf8               java/io/ByteArrayOutputStream
  #435 = Methodref          #433.#40      // java/io/ByteArrayOutputStream."<init>":()V
  #436 = Class              #437          // java/util/zip/ZipFile
  #437 = Utf8               java/util/zip/ZipFile
  #438 = Methodref          #436.#107     // java/util/zip/ZipFile."<init>":(Ljava/lang/String;)V
  #439 = Methodref          #436.#440     // java/util/zip/ZipFile.getEntry:(Ljava/lang/String;)Ljava/util/zip/ZipEntry;
  #440 = NameAndType        #441:#442     // getEntry:(Ljava/lang/String;)Ljava/util/zip/ZipEntry;
  #441 = Utf8               getEntry
  #442 = Utf8               (Ljava/lang/String;)Ljava/util/zip/ZipEntry;
  #443 = Methodref          #436.#444     // java/util/zip/ZipFile.getInputStream:(Ljava/util/zip/ZipEntry;)Ljava/io/InputStream;
  #444 = NameAndType        #445:#446     // getInputStream:(Ljava/util/zip/ZipEntry;)Ljava/io/InputStream;
  #445 = Utf8               getInputStream
  #446 = Utf8               (Ljava/util/zip/ZipEntry;)Ljava/io/InputStream;
  #447 = Methodref          #1.#448       // com/fss/plugin/ParseResouce.copyInputStream:(Ljava/io/InputStream;Ljava/io/OutputStream;)V
  #448 = NameAndType        #449:#450     // copyInputStream:(Ljava/io/InputStream;Ljava/io/OutputStream;)V
  #449 = Utf8               copyInputStream
  #450 = Utf8               (Ljava/io/InputStream;Ljava/io/OutputStream;)V
  #451 = Methodref          #436.#145     // java/util/zip/ZipFile.close:()V
  #452 = Methodref          #433.#453     // java/io/ByteArrayOutputStream.toByteArray:()[B
  #453 = NameAndType        #454:#322     // toByteArray:()[B
  #454 = Utf8               toByteArray
  #455 = Utf8               entryName
  #456 = Utf8               zipFile
  #457 = Utf8               Ljava/util/zip/ZipFile;
  #458 = Utf8               Ljava/io/ByteArrayOutputStream;
  #459 = Utf8               entry
  #460 = Utf8               Ljava/util/zip/ZipEntry;
  #461 = Class              #462          // java/util/zip/ZipEntry
  #462 = Utf8               java/util/zip/ZipEntry
  #463 = Methodref          #402.#464     // java/io/OutputStream.write:([BII)V
  #464 = NameAndType        #405:#465     // write:([BII)V
  #465 = Utf8               ([BII)V
  #466 = Methodref          #143.#398     // java/io/InputStream.read:([B)I
  #467 = Utf8               in
  #468 = Utf8               out
  #469 = Utf8               buffer
  #470 = String             #471          // DESede/ECB/PKCS5Padding
  #471 = Utf8               DESede/ECB/PKCS5Padding
  #472 = Methodref          #473.#475     // javax/crypto/Cipher.getInstance:(Ljava/lang/String;)Ljavax/crypto/Cipher;
  #473 = Class              #474          // javax/crypto/Cipher
  #474 = Utf8               javax/crypto/Cipher
  #475 = NameAndType        #119:#476     // getInstance:(Ljava/lang/String;)Ljavax/crypto/Cipher;
  #476 = Utf8               (Ljava/lang/String;)Ljavax/crypto/Cipher;
  #477 = Methodref          #473.#478     // javax/crypto/Cipher.init:(ILjava/security/Key;)V
  #478 = NameAndType        #479:#480     // init:(ILjava/security/Key;)V
  #479 = Utf8               init
  #480 = Utf8               (ILjava/security/Key;)V
  #481 = Methodref          #473.#482     // javax/crypto/Cipher.getOutputSize:(I)I
  #482 = NameAndType        #483:#484     // getOutputSize:(I)I
  #483 = Utf8               getOutputSize
  #484 = Utf8               (I)I
  #485 = Methodref          #473.#486     // javax/crypto/Cipher.update:([BII[BI)I
  #486 = NameAndType        #487:#488     // update:([BII[BI)I
  #487 = Utf8               update
  #488 = Utf8               ([BII[BI)I
  #489 = Methodref          #473.#490     // javax/crypto/Cipher.doFinal:([BI)I
  #490 = NameAndType        #491:#492     // doFinal:([BI)I
  #491 = Utf8               doFinal
  #492 = Utf8               ([BI)I
  #493 = Methodref          #494.#496     // java/lang/System.arraycopy:(Ljava/lang/Object;ILjava/lang/Object;II)V
  #494 = Class              #495          // java/lang/System
  #495 = Utf8               java/lang/System
  #496 = NameAndType        #497:#498     // arraycopy:(Ljava/lang/Object;ILjava/lang/Object;II)V
  #497 = Utf8               arraycopy
  #498 = Utf8               (Ljava/lang/Object;ILjava/lang/Object;II)V
  #499 = Utf8               cipherText
  #500 = Utf8               cipher
  #501 = Utf8               Ljavax/crypto/Cipher;
  #502 = Utf8               plainTextLength
  #503 = Utf8               tmpPlainText
  #504 = Utf8               ptLength
  #505 = Utf8               plainText
  #506 = Methodref          #25.#507      // java/io/File.delete:()Z
  #507 = NameAndType        #508:#112     // delete:()Z
  #508 = Utf8               delete
  #509 = Utf8               filePath
  #510 = Utf8               SourceFile
  #511 = Utf8               ParseResouce.java
{
  public static final java.lang.String SEPERATOR;
    descriptor: Ljava/lang/String;
    flags: (0x0019) ACC_PUBLIC, ACC_STATIC, ACC_FINAL

  public static java.security.Key DEK;
    descriptor: Ljava/security/Key;
    flags: (0x0009) ACC_PUBLIC, ACC_STATIC

  public static java.lang.String KEYSTORE_PWD;
    descriptor: Ljava/lang/String;
    flags: (0x0009) ACC_PUBLIC, ACC_STATIC

  public static java.lang.String KEY_PWD;
    descriptor: Ljava/lang/String;
    flags: (0x0009) ACC_PUBLIC, ACC_STATIC

  static {};
    descriptor: ()V
    flags: (0x0008) ACC_STATIC
    Code:
      stack=2, locals=0, args_size=0
         0: getstatic     #24                 // Field java/io/File.separator:Ljava/lang/String;
         3: putstatic     #29                 // Field SEPERATOR:Ljava/lang/String;
         6: aconst_null
         7: putstatic     #31                 // Field DEK:Ljava/security/Key;
        10: aconst_null
        11: putstatic     #33                 // Field KEYSTORE_PWD:Ljava/lang/String;
        14: aconst_null
        15: putstatic     #35                 // Field KEY_PWD:Ljava/lang/String;
        18: new           #37                 // class org/bouncycastle/jce/provider/BouncyCastleProvider
        21: dup
        22: invokespecial #39                 // Method org/bouncycastle/jce/provider/BouncyCastleProvider."<init>":()V
        25: invokestatic  #42                 // Method java/security/Security.addProvider:(Ljava/security/Provider;)I
        28: pop
        29: return
      LineNumberTable:
        line 35: 0
        line 39: 6
        line 40: 10
        line 41: 14
        line 516: 18
        line 517: 29
      LocalVariableTable:
        Start  Length  Slot  Name   Signature

  public com.fss.plugin.ParseResouce();
    descriptor: ()V
    flags: (0x0001) ACC_PUBLIC
    Code:
      stack=1, locals=1, args_size=1
         0: aload_0
         1: invokespecial #50                 // Method java/lang/Object."<init>":()V
         4: return
      LineNumberTable:
        line 33: 0
      LocalVariableTable:
        Start  Length  Slot  Name   Signature
            0       5     0  this   Lcom/fss/plugin/ParseResouce;

  public static java.security.Key loadOldKeyStore(java.lang.String) throws java.lang.Exception;
    descriptor: (Ljava/lang/String;)Ljava/security/Key;
    flags: (0x0009) ACC_PUBLIC, ACC_STATIC
    Exceptions:
      throws java.lang.Exception
    Code:
      stack=1, locals=2, args_size=1
         0: aconst_null
         1: astore_1
         2: aload_0
         3: invokestatic  #58                 // Method loadOldKeys:(Ljava/lang/String;)Ljava/security/Key;
         6: astore_1
         7: aload_1
         8: areturn
      LineNumberTable:
        line 44: 0
        line 45: 2
        line 46: 7
      LocalVariableTable:
        Start  Length  Slot  Name   Signature
            0       9     0 keystorePath   Ljava/lang/String;
            2       7     1   key   Ljava/security/Key;

  public static java.security.Key loadNewKeyStore(java.lang.String) throws java.lang.Exception;
    descriptor: (Ljava/lang/String;)Ljava/security/Key;
    flags: (0x0009) ACC_PUBLIC, ACC_STATIC
    Exceptions:
      throws java.lang.Exception
    Code:
      stack=1, locals=2, args_size=1
         0: aconst_null
         1: astore_1
         2: aload_0
         3: invokestatic  #91                 // Method loadNewKeys:(Ljava/lang/String;)Ljava/security/Key;
         6: astore_1
         7: aload_1
         8: areturn
      LineNumberTable:
        line 109: 0
        line 110: 2
        line 111: 7
      LocalVariableTable:
        Start  Length  Slot  Name   Signature
            0       9     0 keystorePath   Ljava/lang/String;
            2       7     1   key   Ljava/security/Key;

  public static java.lang.String hexString(byte[]);
    descriptor: ([B)Ljava/lang/String;
    flags: (0x0009) ACC_PUBLIC, ACC_STATIC
    Code:
      stack=4, locals=5, args_size=1
         0: new           #175                // class java/lang/StringBuffer
         3: dup
         4: aload_0
         5: arraylength
         6: iconst_2
         7: imul
         8: invokespecial #177                // Method java/lang/StringBuffer."<init>":(I)V
        11: astore_1
        12: iconst_0
        13: istore_2
        14: goto          66
        17: aload_0
        18: iload_2
        19: baload
        20: iconst_4
        21: iushr
        22: bipush        15
        24: iand
        25: bipush        16
        27: invokestatic  #180                // Method java/lang/Character.forDigit:(II)C
        30: istore_3
        31: aload_0
        32: iload_2
        33: baload
        34: bipush        15
        36: iand
        37: bipush        16
        39: invokestatic  #180                // Method java/lang/Character.forDigit:(II)C
        42: istore        4
        44: aload_1
        45: iload_3
        46: invokestatic  #186                // Method java/lang/Character.toUpperCase:(C)C
        49: invokevirtual #190                // Method java/lang/StringBuffer.append:(C)Ljava/lang/StringBuffer;
        52: pop
        53: aload_1
        54: iload         4
        56: invokestatic  #186                // Method java/lang/Character.toUpperCase:(C)C
        59: invokevirtual #190                // Method java/lang/StringBuffer.append:(C)Ljava/lang/StringBuffer;
        62: pop
        63: iinc          2, 1
        66: iload_2
        67: aload_0
        68: arraylength
        69: if_icmplt     17
        72: aload_1
        73: invokevirtual #194                // Method java/lang/StringBuffer.toString:()Ljava/lang/String;
        76: areturn
      LineNumberTable:
        line 162: 0
        line 163: 12
        line 164: 17
        line 165: 31
        line 166: 44
        line 167: 53
        line 163: 63
        line 169: 72
      LocalVariableTable:
        Start  Length  Slot  Name   Signature
            0      77     0 abyte0   [B
           12      65     1 stringbuffer   Ljava/lang/StringBuffer;
           14      58     2     i   I
           31      32     3     c   C
           44      19     4    c1   C
      StackMapTable: number_of_entries = 2
        frame_type = 253 /* append */
          offset_delta = 17
          locals = [ class java/lang/StringBuffer, int ]
        frame_type = 48 /* same */

  public static java.lang.String hex2Alpha(java.lang.String);
    descriptor: (Ljava/lang/String;)Ljava/lang/String;
    flags: (0x0009) ACC_PUBLIC, ACC_STATIC
    Code:
      stack=4, locals=5, args_size=1
         0: aload_0
         1: invokevirtual #206                // Method java/lang/String.length:()I
         4: istore_1
         5: new           #175                // class java/lang/StringBuffer
         8: dup
         9: invokespecial #210                // Method java/lang/StringBuffer."<init>":()V
        12: astore_2
        13: iconst_0
        14: istore_3
        15: goto          47
        18: iload_3
        19: iconst_2
        20: iadd
        21: istore        4
        23: aload_2
        24: aload_0
        25: iload_3
        26: iload         4
        28: invokevirtual #211                // Method java/lang/String.substring:(II)Ljava/lang/String;
        31: bipush        16
        33: invokestatic  #215                // Method java/lang/Integer.valueOf:(Ljava/lang/String;I)Ljava/lang/Integer;
        36: invokevirtual #221                // Method java/lang/Integer.intValue:()I
        39: i2c
        40: invokevirtual #190                // Method java/lang/StringBuffer.append:(C)Ljava/lang/StringBuffer;
        43: pop
        44: iinc          3, 2
        47: iload_3
        48: iload_1
        49: if_icmplt     18
        52: aload_2
        53: invokevirtual #194                // Method java/lang/StringBuffer.toString:()Ljava/lang/String;
        56: astore_0
        57: aload_0
        58: areturn
      LineNumberTable:
        line 173: 0
        line 174: 5
        line 175: 13
        line 176: 18
        line 177: 23
        line 178: 36
        line 177: 40
        line 175: 44
        line 180: 52
        line 181: 57
      LocalVariableTable:
        Start  Length  Slot  Name   Signature
            0      59     0  data   Ljava/lang/String;
            5      54     1   len   I
           13      46     2    sb   Ljava/lang/StringBuffer;
           15      37     3     i   I
           23      21     4     j   I
      StackMapTable: number_of_entries = 2
        frame_type = 254 /* append */
          offset_delta = 18
          locals = [ int, class java/lang/StringBuffer, int ]
        frame_type = 28 /* same */

  public static java.lang.String alpha2Hex(java.lang.String);
    descriptor: (Ljava/lang/String;)Ljava/lang/String;
    flags: (0x0009) ACC_PUBLIC, ACC_STATIC
    Code:
      stack=3, locals=5, args_size=1
         0: aload_0
         1: invokevirtual #167                // Method java/lang/String.toCharArray:()[C
         4: astore_1
         5: new           #175                // class java/lang/StringBuffer
         8: dup
         9: invokespecial #210                // Method java/lang/StringBuffer."<init>":()V
        12: astore_2
        13: iconst_0
        14: istore_3
        15: goto          77
        18: aload_1
        19: iload_3
        20: caload
        21: invokestatic  #229                // Method java/lang/Integer.toHexString:(I)Ljava/lang/String;
        24: invokevirtual #233                // Method java/lang/String.toUpperCase:()Ljava/lang/String;
        27: invokevirtual #206                // Method java/lang/String.length:()I
        30: istore        4
        32: iload         4
        34: iconst_1
        35: if_icmpgt     60
        38: aload_2
        39: ldc           #235                // String 0
        41: invokevirtual #237                // Method java/lang/StringBuffer.append:(Ljava/lang/String;)Ljava/lang/StringBuffer;
        44: aload_1
        45: iload_3
        46: caload
        47: invokestatic  #229                // Method java/lang/Integer.toHexString:(I)Ljava/lang/String;
        50: invokevirtual #233                // Method java/lang/String.toUpperCase:()Ljava/lang/String;
        53: invokevirtual #237                // Method java/lang/StringBuffer.append:(Ljava/lang/String;)Ljava/lang/StringBuffer;
        56: pop
        57: goto          74
        60: aload_2
        61: aload_1
        62: iload_3
        63: caload
        64: invokestatic  #229                // Method java/lang/Integer.toHexString:(I)Ljava/lang/String;
        67: invokevirtual #233                // Method java/lang/String.toUpperCase:()Ljava/lang/String;
        70: invokevirtual #237                // Method java/lang/StringBuffer.append:(Ljava/lang/String;)Ljava/lang/StringBuffer;
        73: pop
        74: iinc          3, 1
        77: iload_3
        78: aload_1
        79: arraylength
        80: if_icmplt     18
        83: aload_2
        84: invokevirtual #194                // Method java/lang/StringBuffer.toString:()Ljava/lang/String;
        87: areturn
      LineNumberTable:
        line 185: 0
        line 186: 5
        line 187: 13
        line 188: 18
        line 189: 32
        line 190: 38
        line 191: 44
        line 190: 53
        line 192: 57
        line 193: 60
        line 187: 74
        line 196: 83
      LocalVariableTable:
        Start  Length  Slot  Name   Signature
            0      88     0  data   Ljava/lang/String;
            5      83     1 alpha   [C
           13      75     2    sb   Ljava/lang/StringBuffer;
           15      68     3     i   I
           32      42     4 count   I
      StackMapTable: number_of_entries = 4
        frame_type = 254 /* append */
          offset_delta = 18
          locals = [ class "[C", class java/lang/StringBuffer, int ]
        frame_type = 252 /* append */
          offset_delta = 41
          locals = [ int ]
        frame_type = 250 /* chop */
          offset_delta = 13
        frame_type = 2 /* same */

  public java.lang.String getCGNData(java.lang.String, java.lang.String, java.security.Key);
    descriptor: (Ljava/lang/String;Ljava/lang/String;Ljava/security/Key;)Ljava/lang/String;
    flags: (0x0001) ACC_PUBLIC
    Code:
      stack=5, locals=7, args_size=4
         0: aload_0
         1: aload_1
         2: aload_3
         3: invokespecial #251                // Method createCGZFileFromCGN:(Ljava/lang/String;Ljava/security/Key;)Ljava/lang/String;
         6: astore        4
         8: aload         4
        10: ifnull        341
        13: aload         4
        15: ldc           #255                // String !!Exception!!
        17: invokevirtual #257                // Method java/lang/String.contains:(Ljava/lang/CharSequence;)Z
        20: ifeq          341
        23: aload         4
        25: areturn
        26: astore        4
        28: new           #65                 // class java/lang/String
        31: dup
        32: new           #261                // class java/lang/StringBuilder
        35: dup
        36: ldc_w         #263                // String !!Exception!! while retrieving cgn data :
        39: invokespecial #265                // Method java/lang/StringBuilder."<init>":(Ljava/lang/String;)V
        42: aload         4
        44: invokevirtual #266                // Method java/security/InvalidKeyException.getMessage:()Ljava/lang/String;
        47: invokevirtual #271                // Method java/lang/StringBuilder.append:(Ljava/lang/String;)Ljava/lang/StringBuilder;
        50: getstatic     #274                // Field com/fss/plugin/MAC.fullErrorSplliter:Ljava/lang/String;
        53: invokevirtual #271                // Method java/lang/StringBuilder.append:(Ljava/lang/String;)Ljava/lang/StringBuilder;
        56: aload         4
        58: invokestatic  #279                // Method com/fss/plugin/MAC.fullStackTrace:(Ljava/lang/Exception;)Ljava/lang/String;
        61: invokevirtual #271                // Method java/lang/StringBuilder.append:(Ljava/lang/String;)Ljava/lang/StringBuilder;
        64: invokevirtual #283                // Method java/lang/StringBuilder.toString:()Ljava/lang/String;
        67: invokespecial #284                // Method java/lang/String."<init>":(Ljava/lang/String;)V
        70: areturn
        71: astore        4
        73: new           #65                 // class java/lang/String
        76: dup
        77: new           #261                // class java/lang/StringBuilder
        80: dup
        81: ldc_w         #263                // String !!Exception!! while retrieving cgn data :
        84: invokespecial #265                // Method java/lang/StringBuilder."<init>":(Ljava/lang/String;)V
        87: aload         4
        89: invokevirtual #285                // Method java/security/NoSuchAlgorithmException.getMessage:()Ljava/lang/String;
        92: invokevirtual #271                // Method java/lang/StringBuilder.append:(Ljava/lang/String;)Ljava/lang/StringBuilder;
        95: getstatic     #274                // Field com/fss/plugin/MAC.fullErrorSplliter:Ljava/lang/String;
        98: invokevirtual #271                // Method java/lang/StringBuilder.append:(Ljava/lang/String;)Ljava/lang/StringBuilder;
       101: aload         4
       103: invokestatic  #279                // Method com/fss/plugin/MAC.fullStackTrace:(Ljava/lang/Exception;)Ljava/lang/String;
       106: invokevirtual #271                // Method java/lang/StringBuilder.append:(Ljava/lang/String;)Ljava/lang/StringBuilder;
       109: invokevirtual #283                // Method java/lang/StringBuilder.toString:()Ljava/lang/String;
       112: invokespecial #284                // Method java/lang/String."<init>":(Ljava/lang/String;)V
       115: areturn
       116: astore        4
       118: new           #65                 // class java/lang/String
       121: dup
       122: new           #261                // class java/lang/StringBuilder
       125: dup
       126: ldc_w         #263                // String !!Exception!! while retrieving cgn data :
       129: invokespecial #265                // Method java/lang/StringBuilder."<init>":(Ljava/lang/String;)V
       132: aload         4
       134: invokevirtual #286                // Method javax/crypto/NoSuchPaddingException.getMessage:()Ljava/lang/String;
       137: invokevirtual #271                // Method java/lang/StringBuilder.append:(Ljava/lang/String;)Ljava/lang/StringBuilder;
       140: getstatic     #274                // Field com/fss/plugin/MAC.fullErrorSplliter:Ljava/lang/String;
       143: invokevirtual #271                // Method java/lang/StringBuilder.append:(Ljava/lang/String;)Ljava/lang/StringBuilder;
       146: aload         4
       148: invokestatic  #279                // Method com/fss/plugin/MAC.fullStackTrace:(Ljava/lang/Exception;)Ljava/lang/String;
       151: invokevirtual #271                // Method java/lang/StringBuilder.append:(Ljava/lang/String;)Ljava/lang/StringBuilder;
       154: invokevirtual #283                // Method java/lang/StringBuilder.toString:()Ljava/lang/String;
       157: invokespecial #284                // Method java/lang/String."<init>":(Ljava/lang/String;)V
       160: areturn
       161: astore        4
       163: new           #65                 // class java/lang/String
       166: dup
       167: new           #261                // class java/lang/StringBuilder
       170: dup
       171: ldc_w         #263                // String !!Exception!! while retrieving cgn data :
       174: invokespecial #265                // Method java/lang/StringBuilder."<init>":(Ljava/lang/String;)V
       177: aload         4
       179: invokevirtual #289                // Method javax/crypto/ShortBufferException.getMessage:()Ljava/lang/String;
       182: invokevirtual #271                // Method java/lang/StringBuilder.append:(Ljava/lang/String;)Ljava/lang/StringBuilder;
       185: getstatic     #274                // Field com/fss/plugin/MAC.fullErrorSplliter:Ljava/lang/String;
       188: invokevirtual #271                // Method java/lang/StringBuilder.append:(Ljava/lang/String;)Ljava/lang/StringBuilder;
       191: aload         4
       193: invokestatic  #279                // Method com/fss/plugin/MAC.fullStackTrace:(Ljava/lang/Exception;)Ljava/lang/String;
       196: invokevirtual #271                // Method java/lang/StringBuilder.append:(Ljava/lang/String;)Ljava/lang/StringBuilder;
       199: invokevirtual #283                // Method java/lang/StringBuilder.toString:()Ljava/lang/String;
       202: invokespecial #284                // Method java/lang/String."<init>":(Ljava/lang/String;)V
       205: areturn
       206: astore        4
       208: new           #65                 // class java/lang/String
       211: dup
       212: new           #261                // class java/lang/StringBuilder
       215: dup
       216: ldc_w         #263                // String !!Exception!! while retrieving cgn data :
       219: invokespecial #265                // Method java/lang/StringBuilder."<init>":(Ljava/lang/String;)V
       222: aload         4
       224: invokevirtual #292                // Method javax/crypto/IllegalBlockSizeException.getMessage:()Ljava/lang/String;
       227: invokevirtual #271                // Method java/lang/StringBuilder.append:(Ljava/lang/String;)Ljava/lang/StringBuilder;
       230: getstatic     #274                // Field com/fss/plugin/MAC.fullErrorSplliter:Ljava/lang/String;
       233: invokevirtual #271                // Method java/lang/StringBuilder.append:(Ljava/lang/String;)Ljava/lang/StringBuilder;
       236: aload         4
       238: invokestatic  #279                // Method com/fss/plugin/MAC.fullStackTrace:(Ljava/lang/Exception;)Ljava/lang/String;
       241: invokevirtual #271                // Method java/lang/StringBuilder.append:(Ljava/lang/String;)Ljava/lang/StringBuilder;
       244: invokevirtual #283                // Method java/lang/StringBuilder.toString:()Ljava/lang/String;
       247: invokespecial #284                // Method java/lang/String."<init>":(Ljava/lang/String;)V
       250: areturn
       251: astore        4
       253: new           #65                 // class java/lang/String
       256: dup
       257: new           #261                // class java/lang/StringBuilder
       260: dup
       261: ldc_w         #263                // String !!Exception!! while retrieving cgn data :
       264: invokespecial #265                // Method java/lang/StringBuilder."<init>":(Ljava/lang/String;)V
       267: aload         4
       269: invokevirtual #295                // Method javax/crypto/BadPaddingException.getMessage:()Ljava/lang/String;
       272: invokevirtual #271                // Method java/lang/StringBuilder.append:(Ljava/lang/String;)Ljava/lang/StringBuilder;
       275: getstatic     #274                // Field com/fss/plugin/MAC.fullErrorSplliter:Ljava/lang/String;
       278: invokevirtual #271                // Method java/lang/StringBuilder.append:(Ljava/lang/String;)Ljava/lang/StringBuilder;
       281: aload         4
       283: invokestatic  #279                // Method com/fss/plugin/MAC.fullStackTrace:(Ljava/lang/Exception;)Ljava/lang/String;
       286: invokevirtual #271                // Method java/lang/StringBuilder.append:(Ljava/lang/String;)Ljava/lang/StringBuilder;
       289: invokevirtual #283                // Method java/lang/StringBuilder.toString:()Ljava/lang/String;
       292: invokespecial #284                // Method java/lang/String."<init>":(Ljava/lang/String;)V
       295: areturn
       296: astore        4
       298: new           #65                 // class java/lang/String
       301: dup
       302: new           #261                // class java/lang/StringBuilder
       305: dup
       306: ldc_w         #263                // String !!Exception!! while retrieving cgn data :
       309: invokespecial #265                // Method java/lang/StringBuilder."<init>":(Ljava/lang/String;)V
       312: aload         4
       314: invokevirtual #298                // Method java/io/IOException.getMessage:()Ljava/lang/String;
       317: invokevirtual #271                // Method java/lang/StringBuilder.append:(Ljava/lang/String;)Ljava/lang/StringBuilder;
       320: getstatic     #274                // Field com/fss/plugin/MAC.fullErrorSplliter:Ljava/lang/String;
       323: invokevirtual #271                // Method java/lang/StringBuilder.append:(Ljava/lang/String;)Ljava/lang/StringBuilder;
       326: aload         4
       328: invokestatic  #279                // Method com/fss/plugin/MAC.fullStackTrace:(Ljava/lang/Exception;)Ljava/lang/String;
       331: invokevirtual #271                // Method java/lang/StringBuilder.append:(Ljava/lang/String;)Ljava/lang/StringBuilder;
       334: invokevirtual #283                // Method java/lang/StringBuilder.toString:()Ljava/lang/String;
       337: invokespecial #284                // Method java/lang/String."<init>":(Ljava/lang/String;)V
       340: areturn
       341: aconst_null
       342: astore        4
       344: aconst_null
       345: astore        5
       347: aload_0
       348: new           #261                // class java/lang/StringBuilder
       351: dup
       352: aload_2
       353: invokestatic  #299                // Method java/lang/String.valueOf:(Ljava/lang/Object;)Ljava/lang/String;
       356: invokespecial #265                // Method java/lang/StringBuilder."<init>":(Ljava/lang/String;)V
       359: ldc_w         #302                // String .xml
       362: invokevirtual #271                // Method java/lang/StringBuilder.append:(Ljava/lang/String;)Ljava/lang/StringBuilder;
       365: invokevirtual #283                // Method java/lang/StringBuilder.toString:()Ljava/lang/String;
       368: aload_1
       369: invokespecial #304                // Method extractZIPAndReadXML:(Ljava/lang/String;Ljava/lang/String;)[B
       372: astore        4
       374: goto          467
       377: astore        6
       379: new           #65                 // class java/lang/String
       382: dup
       383: new           #261                // class java/lang/StringBuilder
       386: dup
       387: ldc_w         #308                // String !!Exception!! while extracting and reading xml data :
       390: invokespecial #265                // Method java/lang/StringBuilder."<init>":(Ljava/lang/String;)V
       393: aload         6
       395: invokevirtual #310                // Method java/lang/IllegalStateException.getMessage:()Ljava/lang/String;
       398: invokevirtual #271                // Method java/lang/StringBuilder.append:(Ljava/lang/String;)Ljava/lang/StringBuilder;
       401: getstatic     #274                // Field com/fss/plugin/MAC.fullErrorSplliter:Ljava/lang/String;
       404: invokevirtual #271                // Method java/lang/StringBuilder.append:(Ljava/lang/String;)Ljava/lang/StringBuilder;
       407: aload         6
       409: invokestatic  #279                // Method com/fss/plugin/MAC.fullStackTrace:(Ljava/lang/Exception;)Ljava/lang/String;
       412: invokevirtual #271                // Method java/lang/StringBuilder.append:(Ljava/lang/String;)Ljava/lang/StringBuilder;
       415: invokevirtual #283                // Method java/lang/StringBuilder.toString:()Ljava/lang/String;
       418: invokespecial #284                // Method java/lang/String."<init>":(Ljava/lang/String;)V
       421: areturn
       422: astore        6
       424: new           #65                 // class java/lang/String
       427: dup
       428: new           #261                // class java/lang/StringBuilder
       431: dup
       432: ldc_w         #308                // String !!Exception!! while extracting and reading xml data :
       435: invokespecial #265                // Method java/lang/StringBuilder."<init>":(Ljava/lang/String;)V
       438: aload         6
       440: invokevirtual #298                // Method java/io/IOException.getMessage:()Ljava/lang/String;
       443: invokevirtual #271                // Method java/lang/StringBuilder.append:(Ljava/lang/String;)Ljava/lang/StringBuilder;
       446: getstatic     #274                // Field com/fss/plugin/MAC.fullErrorSplliter:Ljava/lang/String;
       449: invokevirtual #271                // Method java/lang/StringBuilder.append:(Ljava/lang/String;)Ljava/lang/StringBuilder;
       452: aload         6
       454: invokestatic  #279                // Method com/fss/plugin/MAC.fullStackTrace:(Ljava/lang/Exception;)Ljava/lang/String;
       457: invokevirtual #271                // Method java/lang/StringBuilder.append:(Ljava/lang/String;)Ljava/lang/StringBuilder;
       460: invokevirtual #283                // Method java/lang/StringBuilder.toString:()Ljava/lang/String;
       463: invokespecial #284                // Method java/lang/String."<init>":(Ljava/lang/String;)V
       466: areturn
       467: aload         4
       469: ifnull        478
       472: aload         4
       474: arraylength
       475: ifgt          525
       478: new           #65                 // class java/lang/String
       481: dup
       482: new           #261                // class java/lang/StringBuilder
       485: dup
       486: ldc_w         #313                // String !!Exception!! Alias Name does not Exits.
       489: invokespecial #265                // Method java/lang/StringBuilder."<init>":(Ljava/lang/String;)V
       492: getstatic     #274                // Field com/fss/plugin/MAC.fullErrorSplliter:Ljava/lang/String;
       495: invokevirtual #271                // Method java/lang/StringBuilder.append:(Ljava/lang/String;)Ljava/lang/StringBuilder;
       498: ldc_w         #315                // String Record not found for this Alias Name
       501: invokevirtual #271                // Method java/lang/StringBuilder.append:(Ljava/lang/String;)Ljava/lang/StringBuilder;
       504: aload_2
       505: invokevirtual #271                // Method java/lang/StringBuilder.append:(Ljava/lang/String;)Ljava/lang/StringBuilder;
       508: ldc_w         #317                // String  in the resource file location :
       511: invokevirtual #271                // Method java/lang/StringBuilder.append:(Ljava/lang/String;)Ljava/lang/StringBuilder;
       514: aload_1
       515: invokevirtual #271                // Method java/lang/StringBuilder.append:(Ljava/lang/String;)Ljava/lang/StringBuilder;
       518: invokevirtual #283                // Method java/lang/StringBuilder.toString:()Ljava/lang/String;
       521: invokespecial #284                // Method java/lang/String."<init>":(Ljava/lang/String;)V
       524: areturn
       525: aload_3
       526: invokeinterface #319,  1          // InterfaceMethod java/security/Key.getEncoded:()[B
       531: astore        6
       533: aload         6
       535: arraylength
       536: bipush        32
       538: if_icmpne     552
       541: aload_3
       542: aload         4
       544: invokestatic  #81                 // Method com/fss/plugin/AESAlgorithm.decrypt:(Ljava/security/Key;[B)[B
       547: astore        5
       549: goto          879
       552: aload_0
       553: aload         4
       555: aload_3
       556: invokespecial #323                // Method decrypt:([BLjava/security/Key;)[B
       559: astore        5
       561: goto          879
       564: astore        6
       566: new           #65                 // class java/lang/String
       569: dup
       570: new           #261                // class java/lang/StringBuilder
       573: dup
       574: ldc_w         #326                // String !!Exception!! while decrypting xml data :
       577: invokespecial #265                // Method java/lang/StringBuilder."<init>":(Ljava/lang/String;)V
       580: aload         6
       582: invokevirtual #266                // Method java/security/InvalidKeyException.getMessage:()Ljava/lang/String;
       585: invokevirtual #271                // Method java/lang/StringBuilder.append:(Ljava/lang/String;)Ljava/lang/StringBuilder;
       588: getstatic     #274                // Field com/fss/plugin/MAC.fullErrorSplliter:Ljava/lang/String;
       591: invokevirtual #271                // Method java/lang/StringBuilder.append:(Ljava/lang/String;)Ljava/lang/StringBuilder;
       594: aload         6
       596: invokestatic  #279                // Method com/fss/plugin/MAC.fullStackTrace:(Ljava/lang/Exception;)Ljava/lang/String;
       599: invokevirtual #271                // Method java/lang/StringBuilder.append:(Ljava/lang/String;)Ljava/lang/StringBuilder;
       602: invokevirtual #283                // Method java/lang/StringBuilder.toString:()Ljava/lang/String;
       605: invokespecial #284                // Method java/lang/String."<init>":(Ljava/lang/String;)V
       608: areturn
       609: astore        6
       611: new           #65                 // class java/lang/String
       614: dup
       615: new           #261                // class java/lang/StringBuilder
       618: dup
       619: ldc_w         #326                // String !!Exception!! while decrypting xml data :
       622: invokespecial #265                // Method java/lang/StringBuilder."<init>":(Ljava/lang/String;)V
       625: aload         6
       627: invokevirtual #285                // Method java/security/NoSuchAlgorithmException.getMessage:()Ljava/lang/String;
       630: invokevirtual #271                // Method java/lang/StringBuilder.append:(Ljava/lang/String;)Ljava/lang/StringBuilder;
       633: getstatic     #274                // Field com/fss/plugin/MAC.fullErrorSplliter:Ljava/lang/String;
       636: invokevirtual #271                // Method java/lang/StringBuilder.append:(Ljava/lang/String;)Ljava/lang/StringBuilder;
       639: aload         6
       641: invokestatic  #279                // Method com/fss/plugin/MAC.fullStackTrace:(Ljava/lang/Exception;)Ljava/lang/String;
       644: invokevirtual #271                // Method java/lang/StringBuilder.append:(Ljava/lang/String;)Ljava/lang/StringBuilder;
       647: invokevirtual #283                // Method java/lang/StringBuilder.toString:()Ljava/lang/String;
       650: invokespecial #284                // Method java/lang/String."<init>":(Ljava/lang/String;)V
       653: areturn
       654: astore        6
       656: new           #65                 // class java/lang/String
       659: dup
       660: new           #261                // class java/lang/StringBuilder
       663: dup
       664: ldc_w         #326                // String !!Exception!! while decrypting xml data :
       667: invokespecial #265                // Method java/lang/StringBuilder."<init>":(Ljava/lang/String;)V
       670: aload         6
       672: invokevirtual #286                // Method javax/crypto/NoSuchPaddingException.getMessage:()Ljava/lang/String;
       675: invokevirtual #271                // Method java/lang/StringBuilder.append:(Ljava/lang/String;)Ljava/lang/StringBuilder;
       678: getstatic     #274                // Field com/fss/plugin/MAC.fullErrorSplliter:Ljava/lang/String;
       681: invokevirtual #271                // Method java/lang/StringBuilder.append:(Ljava/lang/String;)Ljava/lang/StringBuilder;
       684: aload         6
       686: invokestatic  #279                // Method com/fss/plugin/MAC.fullStackTrace:(Ljava/lang/Exception;)Ljava/lang/String;
       689: invokevirtual #271                // Method java/lang/StringBuilder.append:(Ljava/lang/String;)Ljava/lang/StringBuilder;
       692: invokevirtual #283                // Method java/lang/StringBuilder.toString:()Ljava/lang/String;
       695: invokespecial #284                // Method java/lang/String."<init>":(Ljava/lang/String;)V
       698: areturn
       699: astore        6
       701: new           #65                 // class java/lang/String
       704: dup
       705: new           #261                // class java/lang/StringBuilder
       708: dup
       709: ldc_w         #326                // String !!Exception!! while decrypting xml data :
       712: invokespecial #265                // Method java/lang/StringBuilder."<init>":(Ljava/lang/String;)V
       715: aload         6
       717: invokevirtual #289                // Method javax/crypto/ShortBufferException.getMessage:()Ljava/lang/String;
       720: invokevirtual #271                // Method java/lang/StringBuilder.append:(Ljava/lang/String;)Ljava/lang/StringBuilder;
       723: getstatic     #274                // Field com/fss/plugin/MAC.fullErrorSplliter:Ljava/lang/String;
       726: invokevirtual #271                // Method java/lang/StringBuilder.append:(Ljava/lang/String;)Ljava/lang/StringBuilder;
       729: aload         6
       731: invokestatic  #279                // Method com/fss/plugin/MAC.fullStackTrace:(Ljava/lang/Exception;)Ljava/lang/String;
       734: invokevirtual #271                // Method java/lang/StringBuilder.append:(Ljava/lang/String;)Ljava/lang/StringBuilder;
       737: invokevirtual #283                // Method java/lang/StringBuilder.toString:()Ljava/lang/String;
       740: invokespecial #284                // Method java/lang/String."<init>":(Ljava/lang/String;)V
       743: areturn
       744: astore        6
       746: new           #65                 // class java/lang/String
       749: dup
       750: new           #261                // class java/lang/StringBuilder
       753: dup
       754: ldc_w         #326                // String !!Exception!! while decrypting xml data :
       757: invokespecial #265                // Method java/lang/StringBuilder."<init>":(Ljava/lang/String;)V
       760: aload         6
       762: invokevirtual #292                // Method javax/crypto/IllegalBlockSizeException.getMessage:()Ljava/lang/String;
       765: invokevirtual #271                // Method java/lang/StringBuilder.append:(Ljava/lang/String;)Ljava/lang/StringBuilder;
       768: getstatic     #274                // Field com/fss/plugin/MAC.fullErrorSplliter:Ljava/lang/String;
       771: invokevirtual #271                // Method java/lang/StringBuilder.append:(Ljava/lang/String;)Ljava/lang/StringBuilder;
       774: aload         6
       776: invokestatic  #279                // Method com/fss/plugin/MAC.fullStackTrace:(Ljava/lang/Exception;)Ljava/lang/String;
       779: invokevirtual #271                // Method java/lang/StringBuilder.append:(Ljava/lang/String;)Ljava/lang/StringBuilder;
       782: invokevirtual #283                // Method java/lang/StringBuilder.toString:()Ljava/lang/String;
       785: invokespecial #284                // Method java/lang/String."<init>":(Ljava/lang/String;)V
       788: areturn
       789: astore        6
       791: new           #65                 // class java/lang/String
       794: dup
       795: new           #261                // class java/lang/StringBuilder
       798: dup
       799: ldc_w         #326                // String !!Exception!! while decrypting xml data :
       802: invokespecial #265                // Method java/lang/StringBuilder."<init>":(Ljava/lang/String;)V
       805: aload         6
       807: invokevirtual #295                // Method javax/crypto/BadPaddingException.getMessage:()Ljava/lang/String;
       810: invokevirtual #271                // Method java/lang/StringBuilder.append:(Ljava/lang/String;)Ljava/lang/StringBuilder;
       813: getstatic     #274                // Field com/fss/plugin/MAC.fullErrorSplliter:Ljava/lang/String;
       816: invokevirtual #271                // Method java/lang/StringBuilder.append:(Ljava/lang/String;)Ljava/lang/StringBuilder;
       819: aload         6
       821: invokestatic  #279                // Method com/fss/plugin/MAC.fullStackTrace:(Ljava/lang/Exception;)Ljava/lang/String;
       824: invokevirtual #271                // Method java/lang/StringBuilder.append:(Ljava/lang/String;)Ljava/lang/StringBuilder;
       827: invokevirtual #283                // Method java/lang/StringBuilder.toString:()Ljava/lang/String;
       830: invokespecial #284                // Method java/lang/String."<init>":(Ljava/lang/String;)V
       833: areturn
       834: astore        6
       836: new           #65                 // class java/lang/String
       839: dup
       840: new           #261                // class java/lang/StringBuilder
       843: dup
       844: ldc_w         #326                // String !!Exception!! while decrypting xml data :
       847: invokespecial #265                // Method java/lang/StringBuilder."<init>":(Ljava/lang/String;)V
       850: aload         6
       852: invokevirtual #328                // Method java/lang/Exception.getMessage:()Ljava/lang/String;
       855: invokevirtual #271                // Method java/lang/StringBuilder.append:(Ljava/lang/String;)Ljava/lang/StringBuilder;
       858: getstatic     #274                // Field com/fss/plugin/MAC.fullErrorSplliter:Ljava/lang/String;
       861: invokevirtual #271                // Method java/lang/StringBuilder.append:(Ljava/lang/String;)Ljava/lang/StringBuilder;
       864: aload         6
       866: invokestatic  #279                // Method com/fss/plugin/MAC.fullStackTrace:(Ljava/lang/Exception;)Ljava/lang/String;
       869: invokevirtual #271                // Method java/lang/StringBuilder.append:(Ljava/lang/String;)Ljava/lang/StringBuilder;
       872: invokevirtual #283                // Method java/lang/StringBuilder.toString:()Ljava/lang/String;
       875: invokespecial #284                // Method java/lang/String."<init>":(Ljava/lang/String;)V
       878: areturn
       879: aload         5
       881: ifnull        972
       884: aload_0
       885: new           #261                // class java/lang/StringBuilder
       888: dup
       889: aload_1
       890: invokestatic  #299                // Method java/lang/String.valueOf:(Ljava/lang/Object;)Ljava/lang/String;
       893: invokespecial #265                // Method java/lang/StringBuilder."<init>":(Ljava/lang/String;)V
       896: getstatic     #29                 // Field SEPERATOR:Ljava/lang/String;
       899: invokevirtual #271                // Method java/lang/StringBuilder.append:(Ljava/lang/String;)Ljava/lang/StringBuilder;
       902: ldc_w         #329                // String resource.cgz
       905: invokevirtual #271                // Method java/lang/StringBuilder.append:(Ljava/lang/String;)Ljava/lang/StringBuilder;
       908: invokevirtual #283                // Method java/lang/StringBuilder.toString:()Ljava/lang/String;
       911: invokespecial #331                // Method deleteFile:(Ljava/lang/String;)V
       914: goto          962
       917: astore        6
       919: new           #65                 // class java/lang/String
       922: dup
       923: new           #261                // class java/lang/StringBuilder
       926: dup
       927: ldc_w         #334                // String !!Exception!! while deleting cgz file :
       930: invokespecial #265                // Method java/lang/StringBuilder."<init>":(Ljava/lang/String;)V
       933: aload         6
       935: invokevirtual #328                // Method java/lang/Exception.getMessage:()Ljava/lang/String;
       938: invokevirtual #271                // Method java/lang/StringBuilder.append:(Ljava/lang/String;)Ljava/lang/StringBuilder;
       941: getstatic     #274                // Field com/fss/plugin/MAC.fullErrorSplliter:Ljava/lang/String;
       944: invokevirtual #271                // Method java/lang/StringBuilder.append:(Ljava/lang/String;)Ljava/lang/StringBuilder;
       947: aload         6
       949: invokestatic  #279                // Method com/fss/plugin/MAC.fullStackTrace:(Ljava/lang/Exception;)Ljava/lang/String;
       952: invokevirtual #271                // Method java/lang/StringBuilder.append:(Ljava/lang/String;)Ljava/lang/StringBuilder;
       955: invokevirtual #283                // Method java/lang/StringBuilder.toString:()Ljava/lang/String;
       958: invokespecial #284                // Method java/lang/String."<init>":(Ljava/lang/String;)V
       961: areturn
       962: new           #65                 // class java/lang/String
       965: dup
       966: aload         5
       968: invokespecial #85                 // Method java/lang/String."<init>":([B)V
       971: areturn
       972: new           #65                 // class java/lang/String
       975: dup
       976: new           #261                // class java/lang/StringBuilder
       979: dup
       980: ldc_w         #336                // String !!Exception!! While decrypting xml data.
       983: invokespecial #265                // Method java/lang/StringBuilder."<init>":(Ljava/lang/String;)V
       986: getstatic     #274                // Field com/fss/plugin/MAC.fullErrorSplliter:Ljava/lang/String;
       989: invokevirtual #271                // Method java/lang/StringBuilder.append:(Ljava/lang/String;)Ljava/lang/StringBuilder;
       992: ldc_w         #338                // String Error while decrypting xml data or null
       995: invokevirtual #271                // Method java/lang/StringBuilder.append:(Ljava/lang/String;)Ljava/lang/StringBuilder;
       998: invokevirtual #283                // Method java/lang/StringBuilder.toString:()Ljava/lang/String;
      1001: invokespecial #284                // Method java/lang/String."<init>":(Ljava/lang/String;)V
      1004: areturn
      Exception table:
         from    to  target type
             0    25    26   Class java/security/InvalidKeyException
             0    25    71   Class java/security/NoSuchAlgorithmException
             0    25   116   Class javax/crypto/NoSuchPaddingException
             0    25   161   Class javax/crypto/ShortBufferException
             0    25   206   Class javax/crypto/IllegalBlockSizeException
             0    25   251   Class javax/crypto/BadPaddingException
             0    25   296   Class java/io/IOException
           347   374   377   Class java/lang/IllegalStateException
           347   374   422   Class java/io/IOException
           525   561   564   Class java/security/InvalidKeyException
           525   561   609   Class java/security/NoSuchAlgorithmException
           525   561   654   Class javax/crypto/NoSuchPaddingException
           525   561   699   Class javax/crypto/ShortBufferException
           525   561   744   Class javax/crypto/IllegalBlockSizeException
           525   561   789   Class javax/crypto/BadPaddingException
           525   561   834   Class java/lang/Exception
           884   914   917   Class java/lang/Exception
      LineNumberTable:
        line 205: 0
        line 206: 8
        line 207: 23
        line 210: 26
        line 211: 28
        line 212: 71
        line 213: 73
        line 214: 116
        line 215: 118
        line 216: 161
        line 217: 163
        line 218: 206
        line 219: 208
        line 220: 251
        line 221: 253
        line 222: 296
        line 223: 298
        line 227: 341
        line 228: 344
        line 230: 347
        line 233: 374
        line 234: 379
        line 235: 422
        line 236: 424
        line 238: 467
        line 239: 478
        line 244: 525
        line 245: 533
        line 246: 541
        line 247: 549
        line 248: 552
        line 252: 561
        line 253: 566
        line 254: 609
        line 255: 611
        line 256: 654
        line 257: 656
        line 258: 699
        line 259: 701
        line 260: 744
        line 261: 746
        line 262: 789
        line 263: 791
        line 264: 834
        line 265: 836
        line 268: 879
        line 270: 884
        line 271: 914
        line 272: 919
        line 274: 962
        line 276: 972
      LocalVariableTable:
        Start  Length  Slot  Name   Signature
            0    1005     0  this   Lcom/fss/plugin/ParseResouce;
            0    1005     1 resourcePath   Ljava/lang/String;
            0    1005     2 aliasName   Ljava/lang/String;
            0    1005     3   key   Ljava/security/Key;
            8      18     4  resp   Ljava/lang/String;
           28      43     4     e   Ljava/security/InvalidKeyException;
           73      43     4     e   Ljava/security/NoSuchAlgorithmException;
          118      43     4     e   Ljavax/crypto/NoSuchPaddingException;
          163      43     4     e   Ljavax/crypto/ShortBufferException;
          208      43     4     e   Ljavax/crypto/IllegalBlockSizeException;
          253      43     4     e   Ljavax/crypto/BadPaddingException;
          298      43     4     e   Ljava/io/IOException;
          344     661     4 xmlData   [B
          347     658     5 decryptedText   [B
          379      43     6    e1   Ljava/lang/IllegalStateException;
          424      43     6    e1   Ljava/io/IOException;
          533      28     6 keyByte   [B
          566      43     6     e   Ljava/security/InvalidKeyException;
          611      43     6     e   Ljava/security/NoSuchAlgorithmException;
          656      43     6     e   Ljavax/crypto/NoSuchPaddingException;
          701      43     6     e   Ljavax/crypto/ShortBufferException;
          746      43     6     e   Ljavax/crypto/IllegalBlockSizeException;
          791      43     6     e   Ljavax/crypto/BadPaddingException;
          836      43     6     e   Ljava/lang/Exception;
          919      43     6     e   Ljava/lang/Exception;
      StackMapTable: number_of_entries = 25
        frame_type = 90 /* same_locals_1_stack_item */
          stack = [ class java/security/InvalidKeyException ]
        frame_type = 108 /* same_locals_1_stack_item */
          stack = [ class java/security/NoSuchAlgorithmException ]
        frame_type = 108 /* same_locals_1_stack_item */
          stack = [ class javax/crypto/NoSuchPaddingException ]
        frame_type = 108 /* same_locals_1_stack_item */
          stack = [ class javax/crypto/ShortBufferException ]
        frame_type = 108 /* same_locals_1_stack_item */
          stack = [ class javax/crypto/IllegalBlockSizeException ]
        frame_type = 108 /* same_locals_1_stack_item */
          stack = [ class javax/crypto/BadPaddingException ]
        frame_type = 108 /* same_locals_1_stack_item */
          stack = [ class java/io/IOException ]
        frame_type = 44 /* same */
        frame_type = 255 /* full_frame */
          offset_delta = 35
          locals = [ class com/fss/plugin/ParseResouce, class java/lang/String, class java/lang/String, class java/security/Key, class "[B", class "[B" ]
          stack = [ class java/lang/IllegalStateException ]
        frame_type = 108 /* same_locals_1_stack_item */
          stack = [ class java/io/IOException ]
        frame_type = 44 /* same */
        frame_type = 10 /* same */
        frame_type = 46 /* same */
        frame_type = 252 /* append */
          offset_delta = 26
          locals = [ class "[B" ]
        frame_type = 255 /* full_frame */
          offset_delta = 11
          locals = [ class com/fss/plugin/ParseResouce, class java/lang/String, class java/lang/String, class java/security/Key, class "[B", class "[B" ]
          stack = [ class java/security/InvalidKeyException ]
        frame_type = 108 /* same_locals_1_stack_item */
          stack = [ class java/security/NoSuchAlgorithmException ]
        frame_type = 108 /* same_locals_1_stack_item */
          stack = [ class javax/crypto/NoSuchPaddingException ]
        frame_type = 108 /* same_locals_1_stack_item */
          stack = [ class javax/crypto/ShortBufferException ]
        frame_type = 108 /* same_locals_1_stack_item */
          stack = [ class javax/crypto/IllegalBlockSizeException ]
        frame_type = 108 /* same_locals_1_stack_item */
          stack = [ class javax/crypto/BadPaddingException ]
        frame_type = 108 /* same_locals_1_stack_item */
          stack = [ class java/lang/Exception ]
        frame_type = 44 /* same */
        frame_type = 101 /* same_locals_1_stack_item */
          stack = [ class java/lang/Exception ]
        frame_type = 44 /* same */
        frame_type = 9 /* same */

  public java.lang.String getCGNDataAES(java.lang.String, java.lang.String, java.security.Key);
    descriptor: (Ljava/lang/String;Ljava/lang/String;Ljava/security/Key;)Ljava/lang/String;
    flags: (0x0001) ACC_PUBLIC
    Code:
      stack=5, locals=7, args_size=4
         0: aload_0
         1: aload_1
         2: aload_3
         3: invokespecial #359                // Method createCGZFileFromCGNAES:(Ljava/lang/String;Ljava/security/Key;)Ljava/lang/String;
         6: astore        4
         8: aload         4
        10: ifnull        341
        13: aload         4
        15: ldc           #255                // String !!Exception!!
        17: invokevirtual #257                // Method java/lang/String.contains:(Ljava/lang/CharSequence;)Z
        20: ifeq          341
        23: aload         4
        25: areturn
        26: astore        4
        28: new           #65                 // class java/lang/String
        31: dup
        32: new           #261                // class java/lang/StringBuilder
        35: dup
        36: ldc_w         #362                // String !!Exception!! while retrieving AES cgn data :
        39: invokespecial #265                // Method java/lang/StringBuilder."<init>":(Ljava/lang/String;)V
        42: aload         4
        44: invokevirtual #266                // Method java/security/InvalidKeyException.getMessage:()Ljava/lang/String;
        47: invokevirtual #271                // Method java/lang/StringBuilder.append:(Ljava/lang/String;)Ljava/lang/StringBuilder;
        50: getstatic     #274                // Field com/fss/plugin/MAC.fullErrorSplliter:Ljava/lang/String;
        53: invokevirtual #271                // Method java/lang/StringBuilder.append:(Ljava/lang/String;)Ljava/lang/StringBuilder;
        56: aload         4
        58: invokestatic  #279                // Method com/fss/plugin/MAC.fullStackTrace:(Ljava/lang/Exception;)Ljava/lang/String;
        61: invokevirtual #271                // Method java/lang/StringBuilder.append:(Ljava/lang/String;)Ljava/lang/StringBuilder;
        64: invokevirtual #283                // Method java/lang/StringBuilder.toString:()Ljava/lang/String;
        67: invokespecial #284                // Method java/lang/String."<init>":(Ljava/lang/String;)V
        70: areturn
        71: astore        4
        73: new           #65                 // class java/lang/String
        76: dup
        77: new           #261                // class java/lang/StringBuilder
        80: dup
        81: ldc_w         #362                // String !!Exception!! while retrieving AES cgn data :
        84: invokespecial #265                // Method java/lang/StringBuilder."<init>":(Ljava/lang/String;)V
        87: aload         4
        89: invokevirtual #285                // Method java/security/NoSuchAlgorithmException.getMessage:()Ljava/lang/String;
        92: invokevirtual #271                // Method java/lang/StringBuilder.append:(Ljava/lang/String;)Ljava/lang/StringBuilder;
        95: getstatic     #274                // Field com/fss/plugin/MAC.fullErrorSplliter:Ljava/lang/String;
        98: invokevirtual #271                // Method java/lang/StringBuilder.append:(Ljava/lang/String;)Ljava/lang/StringBuilder;
       101: aload         4
       103: invokestatic  #279                // Method com/fss/plugin/MAC.fullStackTrace:(Ljava/lang/Exception;)Ljava/lang/String;
       106: invokevirtual #271                // Method java/lang/StringBuilder.append:(Ljava/lang/String;)Ljava/lang/StringBuilder;
       109: invokevirtual #283                // Method java/lang/StringBuilder.toString:()Ljava/lang/String;
       112: invokespecial #284                // Method java/lang/String."<init>":(Ljava/lang/String;)V
       115: areturn
       116: astore        4
       118: new           #65                 // class java/lang/String
       121: dup
       122: new           #261                // class java/lang/StringBuilder
       125: dup
       126: ldc_w         #362                // String !!Exception!! while retrieving AES cgn data :
       129: invokespecial #265                // Method java/lang/StringBuilder."<init>":(Ljava/lang/String;)V
       132: aload         4
       134: invokevirtual #286                // Method javax/crypto/NoSuchPaddingException.getMessage:()Ljava/lang/String;
       137: invokevirtual #271                // Method java/lang/StringBuilder.append:(Ljava/lang/String;)Ljava/lang/StringBuilder;
       140: getstatic     #274                // Field com/fss/plugin/MAC.fullErrorSplliter:Ljava/lang/String;
       143: invokevirtual #271                // Method java/lang/StringBuilder.append:(Ljava/lang/String;)Ljava/lang/StringBuilder;
       146: aload         4
       148: invokestatic  #279                // Method com/fss/plugin/MAC.fullStackTrace:(Ljava/lang/Exception;)Ljava/lang/String;
       151: invokevirtual #271                // Method java/lang/StringBuilder.append:(Ljava/lang/String;)Ljava/lang/StringBuilder;
       154: invokevirtual #283                // Method java/lang/StringBuilder.toString:()Ljava/lang/String;
       157: invokespecial #284                // Method java/lang/String."<init>":(Ljava/lang/String;)V
       160: areturn
       161: astore        4
       163: new           #65                 // class java/lang/String
       166: dup
       167: new           #261                // class java/lang/StringBuilder
       170: dup
       171: ldc_w         #362                // String !!Exception!! while retrieving AES cgn data :
       174: invokespecial #265                // Method java/lang/StringBuilder."<init>":(Ljava/lang/String;)V
       177: aload         4
       179: invokevirtual #289                // Method javax/crypto/ShortBufferException.getMessage:()Ljava/lang/String;
       182: invokevirtual #271                // Method java/lang/StringBuilder.append:(Ljava/lang/String;)Ljava/lang/StringBuilder;
       185: getstatic     #274                // Field com/fss/plugin/MAC.fullErrorSplliter:Ljava/lang/String;
       188: invokevirtual #271                // Method java/lang/StringBuilder.append:(Ljava/lang/String;)Ljava/lang/StringBuilder;
       191: aload         4
       193: invokestatic  #279                // Method com/fss/plugin/MAC.fullStackTrace:(Ljava/lang/Exception;)Ljava/lang/String;
       196: invokevirtual #271                // Method java/lang/StringBuilder.append:(Ljava/lang/String;)Ljava/lang/StringBuilder;
       199: invokevirtual #283                // Method java/lang/StringBuilder.toString:()Ljava/lang/String;
       202: invokespecial #284                // Method java/lang/String."<init>":(Ljava/lang/String;)V
       205: areturn
       206: astore        4
       208: new           #65                 // class java/lang/String
       211: dup
       212: new           #261                // class java/lang/StringBuilder
       215: dup
       216: ldc_w         #362                // String !!Exception!! while retrieving AES cgn data :
       219: invokespecial #265                // Method java/lang/StringBuilder."<init>":(Ljava/lang/String;)V
       222: aload         4
       224: invokevirtual #292                // Method javax/crypto/IllegalBlockSizeException.getMessage:()Ljava/lang/String;
       227: invokevirtual #271                // Method java/lang/StringBuilder.append:(Ljava/lang/String;)Ljava/lang/StringBuilder;
       230: getstatic     #274                // Field com/fss/plugin/MAC.fullErrorSplliter:Ljava/lang/String;
       233: invokevirtual #271                // Method java/lang/StringBuilder.append:(Ljava/lang/String;)Ljava/lang/StringBuilder;
       236: aload         4
       238: invokestatic  #279                // Method com/fss/plugin/MAC.fullStackTrace:(Ljava/lang/Exception;)Ljava/lang/String;
       241: invokevirtual #271                // Method java/lang/StringBuilder.append:(Ljava/lang/String;)Ljava/lang/StringBuilder;
       244: invokevirtual #283                // Method java/lang/StringBuilder.toString:()Ljava/lang/String;
       247: invokespecial #284                // Method java/lang/String."<init>":(Ljava/lang/String;)V
       250: areturn
       251: astore        4
       253: new           #65                 // class java/lang/String
       256: dup
       257: new           #261                // class java/lang/StringBuilder
       260: dup
       261: ldc_w         #364                // String !!Exception!! while retrieving AES vcgn data :
       264: invokespecial #265                // Method java/lang/StringBuilder."<init>":(Ljava/lang/String;)V
       267: aload         4
       269: invokevirtual #295                // Method javax/crypto/BadPaddingException.getMessage:()Ljava/lang/String;
       272: invokevirtual #271                // Method java/lang/StringBuilder.append:(Ljava/lang/String;)Ljava/lang/StringBuilder;
       275: getstatic     #274                // Field com/fss/plugin/MAC.fullErrorSplliter:Ljava/lang/String;
       278: invokevirtual #271                // Method java/lang/StringBuilder.append:(Ljava/lang/String;)Ljava/lang/StringBuilder;
       281: aload         4
       283: invokestatic  #279                // Method com/fss/plugin/MAC.fullStackTrace:(Ljava/lang/Exception;)Ljava/lang/String;
       286: invokevirtual #271                // Method java/lang/StringBuilder.append:(Ljava/lang/String;)Ljava/lang/StringBuilder;
       289: invokevirtual #283                // Method java/lang/StringBuilder.toString:()Ljava/lang/String;
       292: invokespecial #284                // Method java/lang/String."<init>":(Ljava/lang/String;)V
       295: areturn
       296: astore        4
       298: new           #65                 // class java/lang/String
       301: dup
       302: new           #261                // class java/lang/StringBuilder
       305: dup
       306: ldc_w         #362                // String !!Exception!! while retrieving AES cgn data :
       309: invokespecial #265                // Method java/lang/StringBuilder."<init>":(Ljava/lang/String;)V
       312: aload         4
       314: invokevirtual #298                // Method java/io/IOException.getMessage:()Ljava/lang/String;
       317: invokevirtual #271                // Method java/lang/StringBuilder.append:(Ljava/lang/String;)Ljava/lang/StringBuilder;
       320: getstatic     #274                // Field com/fss/plugin/MAC.fullErrorSplliter:Ljava/lang/String;
       323: invokevirtual #271                // Method java/lang/StringBuilder.append:(Ljava/lang/String;)Ljava/lang/StringBuilder;
       326: aload         4
       328: invokestatic  #279                // Method com/fss/plugin/MAC.fullStackTrace:(Ljava/lang/Exception;)Ljava/lang/String;
       331: invokevirtual #271                // Method java/lang/StringBuilder.append:(Ljava/lang/String;)Ljava/lang/StringBuilder;
       334: invokevirtual #283                // Method java/lang/StringBuilder.toString:()Ljava/lang/String;
       337: invokespecial #284                // Method java/lang/String."<init>":(Ljava/lang/String;)V
       340: areturn
       341: aconst_null
       342: astore        4
       344: aconst_null
       345: astore        5
       347: aload_0
       348: new           #261                // class java/lang/StringBuilder
       351: dup
       352: aload_2
       353: invokestatic  #299                // Method java/lang/String.valueOf:(Ljava/lang/Object;)Ljava/lang/String;
       356: invokespecial #265                // Method java/lang/StringBuilder."<init>":(Ljava/lang/String;)V
       359: ldc_w         #302                // String .xml
       362: invokevirtual #271                // Method java/lang/StringBuilder.append:(Ljava/lang/String;)Ljava/lang/StringBuilder;
       365: invokevirtual #283                // Method java/lang/StringBuilder.toString:()Ljava/lang/String;
       368: aload_1
       369: invokespecial #366                // Method extractZIPAndReadXMLAES:(Ljava/lang/String;Ljava/lang/String;)[B
       372: astore        4
       374: goto          467
       377: astore        6
       379: new           #65                 // class java/lang/String
       382: dup
       383: new           #261                // class java/lang/StringBuilder
       386: dup
       387: ldc_w         #369                // String !!Exception!! while extracting and reading AES xml data :
       390: invokespecial #265                // Method java/lang/StringBuilder."<init>":(Ljava/lang/String;)V
       393: aload         6
       395: invokevirtual #310                // Method java/lang/IllegalStateException.getMessage:()Ljava/lang/String;
       398: invokevirtual #271                // Method java/lang/StringBuilder.append:(Ljava/lang/String;)Ljava/lang/StringBuilder;
       401: getstatic     #274                // Field com/fss/plugin/MAC.fullErrorSplliter:Ljava/lang/String;
       404: invokevirtual #271                // Method java/lang/StringBuilder.append:(Ljava/lang/String;)Ljava/lang/StringBuilder;
       407: aload         6
       409: invokestatic  #279                // Method com/fss/plugin/MAC.fullStackTrace:(Ljava/lang/Exception;)Ljava/lang/String;
       412: invokevirtual #271                // Method java/lang/StringBuilder.append:(Ljava/lang/String;)Ljava/lang/StringBuilder;
       415: invokevirtual #283                // Method java/lang/StringBuilder.toString:()Ljava/lang/String;
       418: invokespecial #284                // Method java/lang/String."<init>":(Ljava/lang/String;)V
       421: areturn
       422: astore        6
       424: new           #65                 // class java/lang/String
       427: dup
       428: new           #261                // class java/lang/StringBuilder
       431: dup
       432: ldc_w         #369                // String !!Exception!! while extracting and reading AES xml data :
       435: invokespecial #265                // Method java/lang/StringBuilder."<init>":(Ljava/lang/String;)V
       438: aload         6
       440: invokevirtual #298                // Method java/io/IOException.getMessage:()Ljava/lang/String;
       443: invokevirtual #271                // Method java/lang/StringBuilder.append:(Ljava/lang/String;)Ljava/lang/StringBuilder;
       446: getstatic     #274                // Field com/fss/plugin/MAC.fullErrorSplliter:Ljava/lang/String;
       449: invokevirtual #271                // Method java/lang/StringBuilder.append:(Ljava/lang/String;)Ljava/lang/StringBuilder;
       452: aload         6
       454: invokestatic  #279                // Method com/fss/plugin/MAC.fullStackTrace:(Ljava/lang/Exception;)Ljava/lang/String;
       457: invokevirtual #271                // Method java/lang/StringBuilder.append:(Ljava/lang/String;)Ljava/lang/StringBuilder;
       460: invokevirtual #283                // Method java/lang/StringBuilder.toString:()Ljava/lang/String;
       463: invokespecial #284                // Method java/lang/String."<init>":(Ljava/lang/String;)V
       466: areturn
       467: aload         4
       469: ifnull        478
       472: aload         4
       474: arraylength
       475: ifgt          525
       478: new           #65                 // class java/lang/String
       481: dup
       482: new           #261                // class java/lang/StringBuilder
       485: dup
       486: ldc_w         #313                // String !!Exception!! Alias Name does not Exits.
       489: invokespecial #265                // Method java/lang/StringBuilder."<init>":(Ljava/lang/String;)V
       492: getstatic     #274                // Field com/fss/plugin/MAC.fullErrorSplliter:Ljava/lang/String;
       495: invokevirtual #271                // Method java/lang/StringBuilder.append:(Ljava/lang/String;)Ljava/lang/StringBuilder;
       498: ldc_w         #315                // String Record not found for this Alias Name
       501: invokevirtual #271                // Method java/lang/StringBuilder.append:(Ljava/lang/String;)Ljava/lang/StringBuilder;
       504: aload_2
       505: invokevirtual #271                // Method java/lang/StringBuilder.append:(Ljava/lang/String;)Ljava/lang/StringBuilder;
       508: ldc_w         #317                // String  in the resource file location :
       511: invokevirtual #271                // Method java/lang/StringBuilder.append:(Ljava/lang/String;)Ljava/lang/StringBuilder;
       514: aload_1
       515: invokevirtual #271                // Method java/lang/StringBuilder.append:(Ljava/lang/String;)Ljava/lang/StringBuilder;
       518: invokevirtual #283                // Method java/lang/StringBuilder.toString:()Ljava/lang/String;
       521: invokespecial #284                // Method java/lang/String."<init>":(Ljava/lang/String;)V
       524: areturn
       525: aload_3
       526: invokeinterface #319,  1          // InterfaceMethod java/security/Key.getEncoded:()[B
       531: astore        6
       533: aload         6
       535: arraylength
       536: bipush        32
       538: if_icmpne     552
       541: aload_3
       542: aload         4
       544: invokestatic  #81                 // Method com/fss/plugin/AESAlgorithm.decrypt:(Ljava/security/Key;[B)[B
       547: astore        5
       549: goto          879
       552: aload_0
       553: aload         4
       555: aload_3
       556: invokespecial #323                // Method decrypt:([BLjava/security/Key;)[B
       559: astore        5
       561: goto          879
       564: astore        6
       566: new           #65                 // class java/lang/String
       569: dup
       570: new           #261                // class java/lang/StringBuilder
       573: dup
       574: ldc_w         #371                // String !!Exception!! while decrypting AES xml data :
       577: invokespecial #265                // Method java/lang/StringBuilder."<init>":(Ljava/lang/String;)V
       580: aload         6
       582: invokevirtual #266                // Method java/security/InvalidKeyException.getMessage:()Ljava/lang/String;
       585: invokevirtual #271                // Method java/lang/StringBuilder.append:(Ljava/lang/String;)Ljava/lang/StringBuilder;
       588: getstatic     #274                // Field com/fss/plugin/MAC.fullErrorSplliter:Ljava/lang/String;
       591: invokevirtual #271                // Method java/lang/StringBuilder.append:(Ljava/lang/String;)Ljava/lang/StringBuilder;
       594: aload         6
       596: invokestatic  #279                // Method com/fss/plugin/MAC.fullStackTrace:(Ljava/lang/Exception;)Ljava/lang/String;
       599: invokevirtual #271                // Method java/lang/StringBuilder.append:(Ljava/lang/String;)Ljava/lang/StringBuilder;
       602: invokevirtual #283                // Method java/lang/StringBuilder.toString:()Ljava/lang/String;
       605: invokespecial #284                // Method java/lang/String."<init>":(Ljava/lang/String;)V
       608: areturn
       609: astore        6
       611: new           #65                 // class java/lang/String
       614: dup
       615: new           #261                // class java/lang/StringBuilder
       618: dup
       619: ldc_w         #371                // String !!Exception!! while decrypting AES xml data :
       622: invokespecial #265                // Method java/lang/StringBuilder."<init>":(Ljava/lang/String;)V
       625: aload         6
       627: invokevirtual #285                // Method java/security/NoSuchAlgorithmException.getMessage:()Ljava/lang/String;
       630: invokevirtual #271                // Method java/lang/StringBuilder.append:(Ljava/lang/String;)Ljava/lang/StringBuilder;
       633: getstatic     #274                // Field com/fss/plugin/MAC.fullErrorSplliter:Ljava/lang/String;
       636: invokevirtual #271                // Method java/lang/StringBuilder.append:(Ljava/lang/String;)Ljava/lang/StringBuilder;
       639: aload         6
       641: invokestatic  #279                // Method com/fss/plugin/MAC.fullStackTrace:(Ljava/lang/Exception;)Ljava/lang/String;
       644: invokevirtual #271                // Method java/lang/StringBuilder.append:(Ljava/lang/String;)Ljava/lang/StringBuilder;
       647: invokevirtual #283                // Method java/lang/StringBuilder.toString:()Ljava/lang/String;
       650: invokespecial #284                // Method java/lang/String."<init>":(Ljava/lang/String;)V
       653: areturn
       654: astore        6
       656: new           #65                 // class java/lang/String
       659: dup
       660: new           #261                // class java/lang/StringBuilder
       663: dup
       664: ldc_w         #371                // String !!Exception!! while decrypting AES xml data :
       667: invokespecial #265                // Method java/lang/StringBuilder."<init>":(Ljava/lang/String;)V
       670: aload         6
       672: invokevirtual #286                // Method javax/crypto/NoSuchPaddingException.getMessage:()Ljava/lang/String;
       675: invokevirtual #271                // Method java/lang/StringBuilder.append:(Ljava/lang/String;)Ljava/lang/StringBuilder;
       678: getstatic     #274                // Field com/fss/plugin/MAC.fullErrorSplliter:Ljava/lang/String;
       681: invokevirtual #271                // Method java/lang/StringBuilder.append:(Ljava/lang/String;)Ljava/lang/StringBuilder;
       684: aload         6
       686: invokestatic  #279                // Method com/fss/plugin/MAC.fullStackTrace:(Ljava/lang/Exception;)Ljava/lang/String;
       689: invokevirtual #271                // Method java/lang/StringBuilder.append:(Ljava/lang/String;)Ljava/lang/StringBuilder;
       692: invokevirtual #283                // Method java/lang/StringBuilder.toString:()Ljava/lang/String;
       695: invokespecial #284                // Method java/lang/String."<init>":(Ljava/lang/String;)V
       698: areturn
       699: astore        6
       701: new           #65                 // class java/lang/String
       704: dup
       705: new           #261                // class java/lang/StringBuilder
       708: dup
       709: ldc_w         #371                // String !!Exception!! while decrypting AES xml data :
       712: invokespecial #265                // Method java/lang/StringBuilder."<init>":(Ljava/lang/String;)V
       715: aload         6
       717: invokevirtual #289                // Method javax/crypto/ShortBufferException.getMessage:()Ljava/lang/String;
       720: invokevirtual #271                // Method java/lang/StringBuilder.append:(Ljava/lang/String;)Ljava/lang/StringBuilder;
       723: getstatic     #274                // Field com/fss/plugin/MAC.fullErrorSplliter:Ljava/lang/String;
       726: invokevirtual #271                // Method java/lang/StringBuilder.append:(Ljava/lang/String;)Ljava/lang/StringBuilder;
       729: aload         6
       731: invokestatic  #279                // Method com/fss/plugin/MAC.fullStackTrace:(Ljava/lang/Exception;)Ljava/lang/String;
       734: invokevirtual #271                // Method java/lang/StringBuilder.append:(Ljava/lang/String;)Ljava/lang/StringBuilder;
       737: invokevirtual #283                // Method java/lang/StringBuilder.toString:()Ljava/lang/String;
       740: invokespecial #284                // Method java/lang/String."<init>":(Ljava/lang/String;)V
       743: areturn
       744: astore        6
       746: new           #65                 // class java/lang/String
       749: dup
       750: new           #261                // class java/lang/StringBuilder
       753: dup
       754: ldc_w         #371                // String !!Exception!! while decrypting AES xml data :
       757: invokespecial #265                // Method java/lang/StringBuilder."<init>":(Ljava/lang/String;)V
       760: aload         6
       762: invokevirtual #292                // Method javax/crypto/IllegalBlockSizeException.getMessage:()Ljava/lang/String;
       765: invokevirtual #271                // Method java/lang/StringBuilder.append:(Ljava/lang/String;)Ljava/lang/StringBuilder;
       768: getstatic     #274                // Field com/fss/plugin/MAC.fullErrorSplliter:Ljava/lang/String;
       771: invokevirtual #271                // Method java/lang/StringBuilder.append:(Ljava/lang/String;)Ljava/lang/StringBuilder;
       774: aload         6
       776: invokestatic  #279                // Method com/fss/plugin/MAC.fullStackTrace:(Ljava/lang/Exception;)Ljava/lang/String;
       779: invokevirtual #271                // Method java/lang/StringBuilder.append:(Ljava/lang/String;)Ljava/lang/StringBuilder;
       782: invokevirtual #283                // Method java/lang/StringBuilder.toString:()Ljava/lang/String;
       785: invokespecial #284                // Method java/lang/String."<init>":(Ljava/lang/String;)V
       788: areturn
       789: astore        6
       791: new           #65                 // class java/lang/String
       794: dup
       795: new           #261                // class java/lang/StringBuilder
       798: dup
       799: ldc_w         #371                // String !!Exception!! while decrypting AES xml data :
       802: invokespecial #265                // Method java/lang/StringBuilder."<init>":(Ljava/lang/String;)V
       805: aload         6
       807: invokevirtual #295                // Method javax/crypto/BadPaddingException.getMessage:()Ljava/lang/String;
       810: invokevirtual #271                // Method java/lang/StringBuilder.append:(Ljava/lang/String;)Ljava/lang/StringBuilder;
       813: getstatic     #274                // Field com/fss/plugin/MAC.fullErrorSplliter:Ljava/lang/String;
       816: invokevirtual #271                // Method java/lang/StringBuilder.append:(Ljava/lang/String;)Ljava/lang/StringBuilder;
       819: aload         6
       821: invokestatic  #279                // Method com/fss/plugin/MAC.fullStackTrace:(Ljava/lang/Exception;)Ljava/lang/String;
       824: invokevirtual #271                // Method java/lang/StringBuilder.append:(Ljava/lang/String;)Ljava/lang/StringBuilder;
       827: invokevirtual #283                // Method java/lang/StringBuilder.toString:()Ljava/lang/String;
       830: invokespecial #284                // Method java/lang/String."<init>":(Ljava/lang/String;)V
       833: areturn
       834: astore        6
       836: new           #65                 // class java/lang/String
       839: dup
       840: new           #261                // class java/lang/StringBuilder
       843: dup
       844: ldc_w         #371                // String !!Exception!! while decrypting AES xml data :
       847: invokespecial #265                // Method java/lang/StringBuilder."<init>":(Ljava/lang/String;)V
       850: aload         6
       852: invokevirtual #328                // Method java/lang/Exception.getMessage:()Ljava/lang/String;
       855: invokevirtual #271                // Method java/lang/StringBuilder.append:(Ljava/lang/String;)Ljava/lang/StringBuilder;
       858: getstatic     #274                // Field com/fss/plugin/MAC.fullErrorSplliter:Ljava/lang/String;
       861: invokevirtual #271                // Method java/lang/StringBuilder.append:(Ljava/lang/String;)Ljava/lang/StringBuilder;
       864: aload         6
       866: invokestatic  #279                // Method com/fss/plugin/MAC.fullStackTrace:(Ljava/lang/Exception;)Ljava/lang/String;
       869: invokevirtual #271                // Method java/lang/StringBuilder.append:(Ljava/lang/String;)Ljava/lang/StringBuilder;
       872: invokevirtual #283                // Method java/lang/StringBuilder.toString:()Ljava/lang/String;
       875: invokespecial #284                // Method java/lang/String."<init>":(Ljava/lang/String;)V
       878: areturn
       879: aload         5
       881: ifnull        972
       884: aload_0
       885: new           #261                // class java/lang/StringBuilder
       888: dup
       889: aload_1
       890: invokestatic  #299                // Method java/lang/String.valueOf:(Ljava/lang/Object;)Ljava/lang/String;
       893: invokespecial #265                // Method java/lang/StringBuilder."<init>":(Ljava/lang/String;)V
       896: getstatic     #29                 // Field SEPERATOR:Ljava/lang/String;
       899: invokevirtual #271                // Method java/lang/StringBuilder.append:(Ljava/lang/String;)Ljava/lang/StringBuilder;
       902: ldc_w         #373                // String AES_resource.cgz
       905: invokevirtual #271                // Method java/lang/StringBuilder.append:(Ljava/lang/String;)Ljava/lang/StringBuilder;
       908: invokevirtual #283                // Method java/lang/StringBuilder.toString:()Ljava/lang/String;
       911: invokespecial #331                // Method deleteFile:(Ljava/lang/String;)V
       914: goto          962
       917: astore        6
       919: new           #65                 // class java/lang/String
       922: dup
       923: new           #261                // class java/lang/StringBuilder
       926: dup
       927: ldc_w         #375                // String !!Exception!! while deleting AES cgz file :
       930: invokespecial #265                // Method java/lang/StringBuilder."<init>":(Ljava/lang/String;)V
       933: aload         6
       935: invokevirtual #328                // Method java/lang/Exception.getMessage:()Ljava/lang/String;
       938: invokevirtual #271                // Method java/lang/StringBuilder.append:(Ljava/lang/String;)Ljava/lang/StringBuilder;
       941: getstatic     #274                // Field com/fss/plugin/MAC.fullErrorSplliter:Ljava/lang/String;
       944: invokevirtual #271                // Method java/lang/StringBuilder.append:(Ljava/lang/String;)Ljava/lang/StringBuilder;
       947: aload         6
       949: invokestatic  #279                // Method com/fss/plugin/MAC.fullStackTrace:(Ljava/lang/Exception;)Ljava/lang/String;
       952: invokevirtual #271                // Method java/lang/StringBuilder.append:(Ljava/lang/String;)Ljava/lang/StringBuilder;
       955: invokevirtual #283                // Method java/lang/StringBuilder.toString:()Ljava/lang/String;
       958: invokespecial #284                // Method java/lang/String."<init>":(Ljava/lang/String;)V
       961: areturn
       962: new           #65                 // class java/lang/String
       965: dup
       966: aload         5
       968: invokespecial #85                 // Method java/lang/String."<init>":([B)V
       971: areturn
       972: new           #65                 // class java/lang/String
       975: dup
       976: new           #261                // class java/lang/StringBuilder
       979: dup
       980: ldc_w         #377                // String !!Exception!! While decrypting AES xml data.
       983: invokespecial #265                // Method java/lang/StringBuilder."<init>":(Ljava/lang/String;)V
       986: getstatic     #274                // Field com/fss/plugin/MAC.fullErrorSplliter:Ljava/lang/String;
       989: invokevirtual #271                // Method java/lang/StringBuilder.append:(Ljava/lang/String;)Ljava/lang/StringBuilder;
       992: ldc_w         #379                // String Error while decrypting AES xml data or null
       995: invokevirtual #271                // Method java/lang/StringBuilder.append:(Ljava/lang/String;)Ljava/lang/StringBuilder;
       998: invokevirtual #283                // Method java/lang/StringBuilder.toString:()Ljava/lang/String;
      1001: invokespecial #284                // Method java/lang/String."<init>":(Ljava/lang/String;)V
      1004: areturn
      Exception table:
         from    to  target type
             0    25    26   Class java/security/InvalidKeyException
             0    25    71   Class java/security/NoSuchAlgorithmException
             0    25   116   Class javax/crypto/NoSuchPaddingException
             0    25   161   Class javax/crypto/ShortBufferException
             0    25   206   Class javax/crypto/IllegalBlockSizeException
             0    25   251   Class javax/crypto/BadPaddingException
             0    25   296   Class java/io/IOException
           347   374   377   Class java/lang/IllegalStateException
           347   374   422   Class java/io/IOException
           525   561   564   Class java/security/InvalidKeyException
           525   561   609   Class java/security/NoSuchAlgorithmException
           525   561   654   Class javax/crypto/NoSuchPaddingException
           525   561   699   Class javax/crypto/ShortBufferException
           525   561   744   Class javax/crypto/IllegalBlockSizeException
           525   561   789   Class javax/crypto/BadPaddingException
           525   561   834   Class java/lang/Exception
           884   914   917   Class java/lang/Exception
      LineNumberTable:
        line 285: 0
        line 286: 8
        line 287: 23
        line 291: 26
        line 292: 28
        line 293: 71
        line 294: 73
        line 295: 116
        line 296: 118
        line 297: 161
        line 298: 163
        line 299: 206
        line 300: 208
        line 301: 251
        line 302: 253
        line 303: 296
        line 304: 298
        line 308: 341
        line 309: 344
        line 311: 347
        line 314: 374
        line 315: 379
        line 316: 422
        line 317: 424
        line 319: 467
        line 320: 478
        line 325: 525
        line 326: 533
        line 327: 541
        line 328: 549
        line 329: 552
        line 333: 561
        line 334: 566
        line 335: 609
        line 336: 611
        line 337: 654
        line 338: 656
        line 339: 699
        line 340: 701
        line 341: 744
        line 342: 746
        line 343: 789
        line 344: 791
        line 345: 834
        line 346: 836
        line 349: 879
        line 351: 884
        line 352: 914
        line 353: 919
        line 355: 962
        line 357: 972
      LocalVariableTable:
        Start  Length  Slot  Name   Signature
            0    1005     0  this   Lcom/fss/plugin/ParseResouce;
            0    1005     1 resourcePath   Ljava/lang/String;
            0    1005     2 aliasName   Ljava/lang/String;
            0    1005     3   key   Ljava/security/Key;
            8      18     4  resp   Ljava/lang/String;
           28      43     4     e   Ljava/security/InvalidKeyException;
           73      43     4     e   Ljava/security/NoSuchAlgorithmException;
          118      43     4     e   Ljavax/crypto/NoSuchPaddingException;
          163      43     4     e   Ljavax/crypto/ShortBufferException;
          208      43     4     e   Ljavax/crypto/IllegalBlockSizeException;
          253      43     4     e   Ljavax/crypto/BadPaddingException;
          298      43     4     e   Ljava/io/IOException;
          344     661     4 xmlData   [B
          347     658     5 decryptedText   [B
          379      43     6    e1   Ljava/lang/IllegalStateException;
          424      43     6    e1   Ljava/io/IOException;
          533      28     6 keyByte   [B
          566      43     6     e   Ljava/security/InvalidKeyException;
          611      43     6     e   Ljava/security/NoSuchAlgorithmException;
          656      43     6     e   Ljavax/crypto/NoSuchPaddingException;
          701      43     6     e   Ljavax/crypto/ShortBufferException;
          746      43     6     e   Ljavax/crypto/IllegalBlockSizeException;
          791      43     6     e   Ljavax/crypto/BadPaddingException;
          836      43     6     e   Ljava/lang/Exception;
          919      43     6     e   Ljava/lang/Exception;
      StackMapTable: number_of_entries = 25
        frame_type = 90 /* same_locals_1_stack_item */
          stack = [ class java/security/InvalidKeyException ]
        frame_type = 108 /* same_locals_1_stack_item */
          stack = [ class java/security/NoSuchAlgorithmException ]
        frame_type = 108 /* same_locals_1_stack_item */
          stack = [ class javax/crypto/NoSuchPaddingException ]
        frame_type = 108 /* same_locals_1_stack_item */
          stack = [ class javax/crypto/ShortBufferException ]
        frame_type = 108 /* same_locals_1_stack_item */
          stack = [ class javax/crypto/IllegalBlockSizeException ]
        frame_type = 108 /* same_locals_1_stack_item */
          stack = [ class javax/crypto/BadPaddingException ]
        frame_type = 108 /* same_locals_1_stack_item */
          stack = [ class java/io/IOException ]
        frame_type = 44 /* same */
        frame_type = 255 /* full_frame */
          offset_delta = 35
          locals = [ class com/fss/plugin/ParseResouce, class java/lang/String, class java/lang/String, class java/security/Key, class "[B", class "[B" ]
          stack = [ class java/lang/IllegalStateException ]
        frame_type = 108 /* same_locals_1_stack_item */
          stack = [ class java/io/IOException ]
        frame_type = 44 /* same */
        frame_type = 10 /* same */
        frame_type = 46 /* same */
        frame_type = 252 /* append */
          offset_delta = 26
          locals = [ class "[B" ]
        frame_type = 255 /* full_frame */
          offset_delta = 11
          locals = [ class com/fss/plugin/ParseResouce, class java/lang/String, class java/lang/String, class java/security/Key, class "[B", class "[B" ]
          stack = [ class java/security/InvalidKeyException ]
        frame_type = 108 /* same_locals_1_stack_item */
          stack = [ class java/security/NoSuchAlgorithmException ]
        frame_type = 108 /* same_locals_1_stack_item */
          stack = [ class javax/crypto/NoSuchPaddingException ]
        frame_type = 108 /* same_locals_1_stack_item */
          stack = [ class javax/crypto/ShortBufferException ]
        frame_type = 108 /* same_locals_1_stack_item */
          stack = [ class javax/crypto/IllegalBlockSizeException ]
        frame_type = 108 /* same_locals_1_stack_item */
          stack = [ class javax/crypto/BadPaddingException ]
        frame_type = 108 /* same_locals_1_stack_item */
          stack = [ class java/lang/Exception ]
        frame_type = 44 /* same */
        frame_type = 101 /* same_locals_1_stack_item */
          stack = [ class java/lang/Exception ]
        frame_type = 44 /* same */
        frame_type = 9 /* same */

  public static final void copyInputStream(java.io.InputStream, java.io.OutputStream) throws java.io.IOException;
    descriptor: (Ljava/io/InputStream;Ljava/io/OutputStream;)V
    flags: (0x0019) ACC_PUBLIC, ACC_STATIC, ACC_FINAL
    Exceptions:
      throws java.io.IOException
    Code:
      stack=4, locals=4, args_size=2
         0: sipush        1024
         3: newarray       byte
         5: astore_2
         6: goto          16
         9: aload_1
        10: aload_2
        11: iconst_0
        12: iload_3
        13: invokevirtual #463                // Method java/io/OutputStream.write:([BII)V
        16: aload_0
        17: aload_2
        18: invokevirtual #466                // Method java/io/InputStream.read:([B)I
        21: dup
        22: istore_3
        23: ifge          9
        26: aload_0
        27: invokevirtual #142                // Method java/io/InputStream.close:()V
        30: aload_1
        31: invokevirtual #417                // Method java/io/OutputStream.close:()V
        34: return
      LineNumberTable:
        line 489: 0
        line 491: 6
        line 492: 9
        line 491: 16
        line 493: 26
        line 494: 30
        line 495: 34
      LocalVariableTable:
        Start  Length  Slot  Name   Signature
            0      35     0    in   Ljava/io/InputStream;
            0      35     1   out   Ljava/io/OutputStream;
            6      29     2 buffer   [B
            9       7     3   len   I
           23      12     3   len   I
      StackMapTable: number_of_entries = 2
        frame_type = 253 /* append */
          offset_delta = 9
          locals = [ class "[B", int ]
        frame_type = 250 /* chop */
          offset_delta = 6
}
SourceFile: "ParseResouce.java"
